cpu/uc.v
module uc(input wire [5:0] opcode, input wire z, output reg s_inc, s_inm, we3, wez, s_pila, push, pop, we4, s_data,  output reg [2:0] op_alu);

always @(opcode)
casez (opcode)
	6'b0zzzzz:   // aritmetica
		begin
			op_alu = opcode[4:2];
			wez = 1; s_inm = 0;
			we3 = 1; s_inc = 1;
			s_pila = 0; push = 0;
			pop = 0; we4 = 0;
		end
	6'b100000:   // carga inmediata
		begin
			s_inm = 1; we3 = 1;
			s_inc = 1; s_pila = 0;
			push = 0; pop = 0;
			s_data = 0; we4 = 0;
		end
	6'b100001:  // salto
		begin
			s_inc = 0; s_pila = 0;
			push = 0; pop = 0;
			we4 = 0;
		end
	6'b100010:  // salto si z
		begin
			s_pila = 0; we4 = 0;
			we3 = 0; wez = 0;
			push = 0; pop = 0;
			// if ( z == 1b'1 ) begin
			if ( z == 1 ) begin
				s_inc = 0;
			end else begin
				s_inc = 1;
			end
		end
	6'b100011: // salto si no z
		begin
			s_pila = 0; we4 = 0;
			we3 = 0; wez = 0;
			push = 0; pop = 0;
			if ( z == 0 ) begin
				s_inc = 0;
			end else begin
				s_inc = 1;
			end
		end
	6'b100100: // push pila
		begin
			s_inc = 1;
			push = 1; pop = 0;
			s_pila = 0;
			we3 = 0; wez = 0;
			we4 = 0;
		end
	6'b100101: // pop pila
		begin
			pop = 1; push = 0;
			s_pila = 1;
			we3 = 0; wez = 0;
			we4 = 0;
		end
	6'b100110: // load word (mem datos ----> banco registros)
		begin
			s_inc = 0; s_pila = 0; 
			we3 = 1; wez = 0;
			we4 = 0; s_data = 1;
			s_inm = 1;
		end
	6'b100111: // save word (banco registros ----> mem datos)
		begin
			s_inc = 0; s_pila = 0;
			we3 = 0; wez = 0;
			we4 = 1; s_data = 1;
			s_inm = 1;
		end

default: ;
endcase

endmodule

cpu/componentes.v
//Componentes varios

//Banco de registros de dos salidas y una entrada
module regfile(input  wire        clk, 
               input  wire        we3,           //señal de habilitación de escritura
               input  wire [3:0]  ra1, ra2, wa3, //direcciones de regs leidos y reg a escribir
               input  wire [7:0]  wd3, 			 //dato a escribir
               output wire [7:0]  rd1, rd2);     //datos leidos

  reg [7:0] regb[0:15]; //memoria de 16 registros de 8 bits de ancho

  initial
  begin
    $readmemb("regfile.dat",regb); // inicializa los registros a valores conocidos
  end  
  
  // El registro 0 siempre es cero
  // se leen dos reg combinacionalmente
  // y la escritura del tercero ocurre en flanco de subida del reloj
  
  always @(posedge clk)
    if (we3) regb[wa3] <= wd3;	
  
  assign rd1 = (ra1 != 0) ? regb[ra1] : 0;
  assign rd2 = (ra2 != 0) ? regb[ra2] : 0;

endmodule

//modulo sumador  
module sum(input  wire [9:0] a, b,
             output wire [9:0] y);

  assign y = a + b;

endmodule

//modulo registro para modelar el PC, cambia en cada flanco de subida de reloj o de reset
module registro #(parameter WIDTH = 8)
              (input wire             clk, reset,
               input wire [WIDTH-1:0] d, 
               output reg [WIDTH-1:0] q);

  always @(posedge clk, posedge reset)
    if (reset) q <= 0;
    else       q <= d;

endmodule

//modulo multiplexor, si s=1 sale d1, s=0 sale d0
module mux2 #(parameter WIDTH = 8)
             (input  wire [WIDTH-1:0] d0, d1, 
              input  wire             s, 
              output wire [WIDTH-1:0] y);

  assign y = s ? d1 : d0; 

endmodule

//Biestable para el flag de cero
//Biestable tipo D síncrono con reset asíncrono por flanco y entrada de habilitación de carga
module ffd(input wire clk, reset, d, carga, output reg q);

  always @(posedge clk, posedge reset)
    if (reset)
	    q <= 1'b0;
	  else
	    if (carga)
	      q <= d;

endmodule 

module  pila(input wire clk, reset, push, pop, input wire [9:0] inpush, output reg [9:0] outpop );
  reg [2:0] sp;
  //integer sp = 0;
  reg [9:0] mem[0:7];
  initial 
    begin
      sp = 0;
    end

    always @(push, pop, posedge reset) begin
	  if ( reset )
		sp = 3'b000;
	if ( push ) 
		begin
	        	mem[sp] = inpush;	
			sp = sp + 3'b001;
		end
	  if ( pop ) 
		begin
			sp = sp - 3'b001;
			outpop = mem[sp];
		end
	end

endmodule

//memoria de datos

module regprog (input wire clk, input wire we4, input wire [5:0] wra, input wire [7:0] wd, output wire [7:0] rd);
	
	// we4 : write enable
	// wra : write/read addres
	// wd : write data
	// rd : read data
	reg [7:0] regb[0:63];  //memoria de 64 de 8 bits de ancho

	initial
	begin
		$readmemb("regdata.dat", regb);
	end
	always @(posedge clk)
		if (we4) regb[wra] <= wd;
	
	assign rd = regb[wra];


endmodule

cpu/alu.v
module alu(input wire [7:0] a, b,
           input wire [2:0] op_alu,
           output wire [7:0] y,
           output wire zero);

reg [7:0] s;		   
		   
always @(a, b, op_alu)
begin
  case (op_alu)              
    3'b000: s = a;
    3'b001: s = ~a;
    3'b010: s = a + b;
    3'b011: s = a - b;
    3'b100: s = a & b;
    3'b101: s = a | b;
    3'b110: s = -a;
    3'b111: s = -b;
	default: s = 'bx; //desconocido en cualquier otro caso (x ó z), por si se modifica el código
  endcase
end

assign y = s;

//Calculo del flag de cero
assign zero = ~(|y);   //operador de reducción |y hace la or de los bits del vector 'y' y devuelve 1 bit resultado
		   
endmodule

cpu/memprog.v
//Memoria de programa, se inicializa y no se modifica

module memprog(input  wire        clk,
               input  wire [9:0]  a,
               output wire [15:0] rd);

  reg [15:0] mem[0:1023]; //memoria de 1024 palabras de 16 bits de ancho

  initial
  begin
    $readmemb("progfile.dat",mem); // inicializa la memoria del fichero en texto binario
  end
  
  assign rd = mem[a];

endmodule

cpu/cd.v
module cd(input wire clk, reset, s_inc, s_inm, we3, wez, s_pila, push, pop, we4,s_data,  input wire [2:0] op_alu, output wire z, output wire [5:0] opcode);
//Camino de datos de instrucciones de un solo ciclo
wire [9:0] mux_to_pc, pc_to_mem, sum_to_mux, mux_to_mux, pila_to_mux;
wire [7:0] rd1, rd2, alu_to_mux, wd3, memdat_to_mux, mux_mem_to_mux_banc;
wire [15:0] sal_mem_pro;
wire zalu;

//1
mux2 #10 mux_1(sal_mem_pro[9:0], sum_to_mux, s_inc, mux_to_mux);
//2
registro #10 pc(clk, reset, mux_to_pc, pc_to_mem);
//3
memprog mem_prog(clk, pc_to_mem, sal_mem_pro);
//4
regfile banco(clk, we3, sal_mem_pro[11:8], sal_mem_pro[7:4], sal_mem_pro[3:0], wd3, rd1, rd2);
//5
mux2 #8 mux_2(alu_to_mux, mux_mem_to_mux_banc, s_inm, wd3);
//6
alu alu1(rd1, rd2, op_alu, alu_to_mux, zalu);
//7
ffd ffz(clk, reset, zalu, wez, z);
//8 
sum sum1(pc_to_mem, 10'b1 , sum_to_mux);
//9 
mux2 #10 mux_3(mux_to_mux, pila_to_mux, s_pila, mux_to_pc);
//10
pila pila1(clk, reset, push, pop, pc_to_mem, pila_to_mux);
//11
regprog regpro1(clk,we4,sal_mem_pro[9:4],rd1,memdat_to_mux);
//12
mux2 #8 mux_4(sal_mem_pro[11:4],memdat_to_mux,s_data,mux_mem_to_mux_banc);

assign opcode = sal_mem_pro[15:10];


endmodule

cpu/cpu.v
module cpu(input wire clk, reset);
//Procesador sin memoria de datos de un solo ciclo

wire s_inc, s_inm, we3, wez, z, s_pila, push, pop, we4, s_data;
wire [5:0] opcode;
wire [2:0] op_alu;

cd cd_1(clk, reset, s_inc, s_inm, we3, wez, s_pila, push, pop, we4, s_data, op_alu, z, opcode);
uc uc_1(opcode, z, s_inc, s_inm, we3, wez, s_pila, push, pop, we4, s_data,  op_alu);




endmodule

cpu/cpu_tb.v
`timescale 1 ns / 10 ps

// unidad de cuenta de simulacion / escala 
// frecuencia = 16'8 mhz

module cpu_tb;


reg clk, reset, ie1, ie2, ie3, ie4;
wire [7:0] o1, o2, o3, o4, i1, i2, i3, i4;

// generación de reloj clk
always //siempre activo, no hay condición de activación
begin
  clk = 1'b1;
  //#30;
  #20; // 50mhz
  clk = 1'b0;
  //#30;
  #20;
end

// instanciación del procesador
cpu micpu(clk, reset, ie1, ie2, ie3, ie4, o1, o2, o3, o4, i1, i2, i3, i4);

initial
begin
  $dumpfile("cpu_tb.vcd");
  //$dumpvars(0,cpu_tb.micpu.cd_1.banco.regb[0]); 
  $dumpvars;
  reset = 1;  //a partir del flanco de subida del reset empieza el funcionamiento normal
  #10;
  reset = 0;  //bajamos el reset 
  ie1 = 0;
  ie2 = 0;
  ie3 = 0;
  ie4 = 0;
end
/*
initial
begin
	#(2*60);
	ie1 = 1;
	#(60);
	ie1 = 0;
end
*/
initial
begin

  //#(9*60);  //Esperamos 9 ciclos o 9 instrucciones
  //#(9*40);  //Esperamos 9 ciclos o 9 instrucciones
  #(50001*40);  //Esperamos 9 ciclos o 9 instrucciones
  $finish;
end

endmodule

cpu/cpu_tb.vcd
$date
	Mon Mar 15 21:16:47 2021
$end
$version
	Icarus Verilog
$end
$timescale
	10ps
$end
$scope module cpu_tb $end
$var reg 1 ! clk $end
$var reg 1 " reset $end
$scope module micpu $end
$var wire 1 ! clk $end
$var wire 1 " reset $end
$var wire 1 # z $end
$var wire 1 $ wez $end
$var wire 1 % we4 $end
$var wire 1 & we3 $end
$var wire 1 ' s_pila $end
$var wire 1 ( s_inm $end
$var wire 1 ) s_inc $end
$var wire 1 * s_data $end
$var wire 1 + push $end
$var wire 1 , pop $end
$var wire 6 - opcode [5:0] $end
$var wire 3 . op_alu [2:0] $end
$scope module cd_1 $end
$var wire 1 ! clk $end
$var wire 1 " reset $end
$var wire 1 / zalu $end
$var wire 1 # z $end
$var wire 1 $ wez $end
$var wire 1 % we4 $end
$var wire 1 & we3 $end
$var wire 8 0 wd3 [7:0] $end
$var wire 10 1 sum_to_mux [9:0] $end
$var wire 16 2 sal_mem_pro [15:0] $end
$var wire 1 ' s_pila $end
$var wire 1 ( s_inm $end
$var wire 1 ) s_inc $end
$var wire 1 * s_data $end
$var wire 8 3 rd2 [7:0] $end
$var wire 8 4 rd1 [7:0] $end
$var wire 1 + push $end
$var wire 1 , pop $end
$var wire 10 5 pila_to_mux [9:0] $end
$var wire 10 6 pc_to_mem [9:0] $end
$var wire 6 7 opcode [5:0] $end
$var wire 3 8 op_alu [2:0] $end
$var wire 10 9 mux_to_pc [9:0] $end
$var wire 10 : mux_to_mux [9:0] $end
$var wire 8 ; mux_mem_to_mux_banc [7:0] $end
$var wire 8 < memdat_to_mux [7:0] $end
$var wire 8 = alu_to_mux [7:0] $end
$scope module alu1 $end
$var wire 8 > y [7:0] $end
$var wire 1 / zero $end
$var wire 3 ? op_alu [2:0] $end
$var wire 8 @ b [7:0] $end
$var wire 8 A a [7:0] $end
$var reg 8 B s [7:0] $end
$upscope $end
$scope module banco $end
$var wire 1 ! clk $end
$var wire 4 C ra1 [3:0] $end
$var wire 4 D ra2 [3:0] $end
$var wire 4 E wa3 [3:0] $end
$var wire 1 & we3 $end
$var wire 8 F wd3 [7:0] $end
$var wire 8 G rd2 [7:0] $end
$var wire 8 H rd1 [7:0] $end
$upscope $end
$scope module ffz $end
$var wire 1 ! clk $end
$var wire 1 / d $end
$var wire 1 " reset $end
$var wire 1 $ carga $end
$var reg 1 # q $end
$upscope $end
$scope module mem_prog $end
$var wire 1 ! clk $end
$var wire 16 I rd [15:0] $end
$var wire 10 J a [9:0] $end
$upscope $end
$scope module mux_1 $end
$var wire 10 K d0 [9:0] $end
$var wire 10 L y [9:0] $end
$var wire 1 ) s $end
$var wire 10 M d1 [9:0] $end
$upscope $end
$scope module mux_2 $end
$var wire 8 N d0 [7:0] $end
$var wire 8 O y [7:0] $end
$var wire 1 ( s $end
$var wire 8 P d1 [7:0] $end
$upscope $end
$scope module mux_3 $end
$var wire 10 Q d0 [9:0] $end
$var wire 10 R y [9:0] $end
$var wire 1 ' s $end
$var wire 10 S d1 [9:0] $end
$upscope $end
$scope module mux_4 $end
$var wire 8 T d0 [7:0] $end
$var wire 8 U y [7:0] $end
$var wire 1 * s $end
$var wire 8 V d1 [7:0] $end
$upscope $end
$scope module pc $end
$var wire 1 ! clk $end
$var wire 10 W d [9:0] $end
$var wire 1 " reset $end
$var reg 10 X q [9:0] $end
$upscope $end
$scope module pila1 $end
$var wire 1 ! clk $end
$var wire 10 Y inpush [9:0] $end
$var wire 1 " reset $end
$var wire 1 + push $end
$var wire 1 , pop $end
$var reg 10 Z outpop [9:0] $end
$var reg 3 [ sp [2:0] $end
$upscope $end
$scope module regpro1 $end
$var wire 1 ! clk $end
$var wire 8 \ rd [7:0] $end
$var wire 8 ] wd [7:0] $end
$var wire 6 ^ wra [5:0] $end
$var wire 1 % we4 $end
$upscope $end
$scope module sum1 $end
$var wire 10 _ a [9:0] $end
$var wire 10 ` b [9:0] $end
$var wire 10 a y [9:0] $end
$upscope $end
$upscope $end
$scope module uc_1 $end
$var wire 6 b opcode [5:0] $end
$var wire 1 # z $end
$var reg 3 c op_alu [2:0] $end
$var reg 1 , pop $end
$var reg 1 + push $end
$var reg 1 * s_data $end
$var reg 1 ) s_inc $end
$var reg 1 ( s_inm $end
$var reg 1 ' s_pila $end
$var reg 1 & we3 $end
$var reg 1 % we4 $end
$var reg 1 $ wez $end
$upscope $end
$upscope $end
$upscope $end
$enddefinitions $end
#0
$dumpvars
bx c
b100110 b
b1 a
b1 `
b0 _
b10 ^
b0 ]
b10 \
b0 [
bx Z
b0 Y
b0 X
b100010 W
b10 V
b10 U
b10000010 T
bx S
b100010 R
b100010 Q
b10 P
b10 O
bx N
b1 M
b100010 L
b100010 K
b0 J
b1001100000100010 I
b0 H
b0 G
b10 F
b10 E
b10 D
b1000 C
bx B
b0 A
b0 @
bx ?
bx >
bx =
b10 <
b10 ;
b100010 :
b100010 9
bx 8
b100110 7
b0 6
bx 5
b0 4
b0 3
b1001100000100010 2
b1 1
b10 0
x/
bx .
b100110 -
x,
x+
1*
0)
1(
0'
1&
0%
0$
0#
1"
1!
$end
#1000
0"
#3000
0!
#6000
1/
b0 =
b0 >
b0 B
b0 N
b0 0
b0 F
b0 O
b100011 9
b100011 R
b100011 W
0,
0+
1)
0(
1$
b0 .
b0 8
b0 ?
b0 c
b0 ;
b0 P
b0 U
b100011 :
b100011 L
b100011 Q
b0 -
b0 7
b0 b
b0 T
b0 <
b0 V
b0 \
b0 ^
b0 E
b0 D
b0 C
b0 K
b100011 1
b100011 M
b100011 a
b0 2
b0 I
b100010 6
b100010 J
b100010 X
b100010 Y
b100010 _
1!
#9000
0!
#12000
b100100 9
b100100 R
b100100 W
b100100 :
b100100 L
b100100 Q
b100100 1
b100100 M
b100100 a
b100011 6
b100011 J
b100011 X
b100011 Y
b100011 _
1#
1!
#15000
0!
#18000
b100101 9
b100101 R
b100101 W
b100101 :
b100101 L
b100101 Q
b100101 1
b100101 M
b100101 a
b100100 6
b100100 J
b100100 X
b100100 Y
b100100 _
1!
#21000
0!
#24000
b100110 9
b100110 R
b100110 W
b100110 :
b100110 L
b100110 Q
b100110 1
b100110 M
b100110 a
b100101 6
b100101 J
b100101 X
b100101 Y
b100101 _
1!
#27000
0!
#30000
b100111 9
b100111 R
b100111 W
b100111 :
b100111 L
b100111 Q
b100111 1
b100111 M
b100111 a
b100110 6
b100110 J
b100110 X
b100110 Y
b100110 _
1!
#33000
0!
#36000
b101000 9
b101000 R
b101000 W
b101000 :
b101000 L
b101000 Q
b101000 1
b101000 M
b101000 a
b100111 6
b100111 J
b100111 X
b100111 Y
b100111 _
1!
#39000
0!
#42000
b101001 9
b101001 R
b101001 W
b101001 :
b101001 L
b101001 Q
b101001 1
b101001 M
b101001 a
b101000 6
b101000 J
b101000 X
b101000 Y
b101000 _
1!
#45000
0!
#48000
b101010 9
b101010 R
b101010 W
b101010 :
b101010 L
b101010 Q
b101010 1
b101010 M
b101010 a
b101001 6
b101001 J
b101001 X
b101001 Y
b101001 _
1!
#51000
0!
#54000
b101011 9
b101011 R
b101011 W
b101011 :
b101011 L
b101011 Q
b101011 1
b101011 M
b101011 a
b101010 6
b101010 J
b101010 X
b101010 Y
b101010 _
1!
