cpu/uc.v
module uc(input wire [5:0] opcode, input wire z, output reg s_inc, we3, wez, s_pila, push, pop, we4, output reg [1:0] s_inm,  output reg [2:0] op_alu);

always @(opcode)
casez (opcode)
	6'b0zzzzz:   // aritmetica
		begin
			op_alu = opcode[4:2];
			wez = 1; s_inm = 2'b00;
			we3 = 1; s_inc = 1;
			s_pila = 0; push = 0;
			pop = 0; we4 = 0;
		end
	6'b100000:   // carga inmediata
		begin
			s_inm = 2'b01; we3 = 1;
			s_inc = 1; s_pila = 0;
			push = 0; pop = 0;
			 we4 = 0;
		end
	6'b100001:  // salto
		begin
			s_inc = 0; s_pila = 0;
			push = 0; pop = 0;
			we4 = 0;
		end
	6'b100010:  // salto si z
		begin
			s_pila = 0; we4 = 0;
			we3 = 0; wez = 0;
			push = 0; pop = 0;
			// if ( z == 1b'1 ) begin
			if ( z == 1 ) begin
				s_inc = 0;
			end else begin
				s_inc = 1;
			end
		end
	6'b100011: // salto si no z
		begin
			s_pila = 0; we4 = 0;
			we3 = 0; wez = 0;
			push = 0; pop = 0;
			if ( z == 0 ) begin
				s_inc = 0;
			end else begin
				s_inc = 1;
			end
		end
	6'b100100: // push pila
		begin
			s_inc = 1;
			push = 1; pop = 0;
			s_pila = 0;
			we3 = 0; wez = 0;
			we4 = 0;
		end
	6'b100101: // pop pila
		begin
			pop = 1; push = 0;
			s_pila = 1;
			we3 = 0; wez = 0;
			we4 = 0;
		end
	6'b111000: // load word (mem datos ----> banco registros)  1110 mem dato[8] banc[4]
		begin
			s_inc = 1; s_pila = 0; 
			we3 = 1; wez = 0;
			we4 = 0; 
			s_inm = 2'b10;
		end
	6'b111100: // save word (banco registros ----> mem datos)  1111 banc[4] mem dato[8]
		begin
			s_inc = 1; s_pila = 0;
			we3 = 0; wez = 0;
			we4 = 1; 
		end

default: ;
endcase

endmodule

cpu/componentes.v
//Componentes varios

//Banco de registros de dos salidas y una entrada
module regfile(input  wire        clk, 
               input  wire        we3,           //señal de habilitación de escritura
               input  wire [3:0]  ra1, ra2, wa3, //direcciones de regs leidos y reg a escribir
               input  wire [7:0]  wd3, 			 //dato a escribir
               output wire [7:0]  rd1, rd2);     //datos leidos

  reg [7:0] regb[0:15]; //memoria de 16 registros de 8 bits de ancho

  initial
  begin
    $readmemb("regfile.dat",regb); // inicializa los registros a valores conocidos
  end  
  
  // El registro 0 siempre es cero
  // se leen dos reg combinacionalmente
  // y la escritura del tercero ocurre en flanco de subida del reloj
  
  always @(posedge clk)
    if (we3) regb[wa3] <= wd3;	
  
  assign rd1 = (ra1 != 0) ? regb[ra1] : 0;
  assign rd2 = (ra2 != 0) ? regb[ra2] : 0;

endmodule

//modulo sumador  
module sum(input  wire [9:0] a, b,
             output wire [9:0] y);

  assign y = a + b;

endmodule

//modulo registro para modelar el PC, cambia en cada flanco de subida de reloj o de reset
module registro #(parameter WIDTH = 8)
              (input wire             clk, reset,
               input wire [WIDTH-1:0] d, 
               output reg [WIDTH-1:0] q);

  always @(posedge clk, posedge reset)
    if (reset) q <= 0;
    else       q <= d;

endmodule

//modulo multiplexor, si s=1 sale d1, s=0 sale d0
module mux2 #(parameter WIDTH = 8)
             (input  wire [WIDTH-1:0] d0, d1, 
              input  wire             s, 
              output wire [WIDTH-1:0] y);

  assign y = s ? d1 : d0; 

endmodule

//Biestable para el flag de cero
//Biestable tipo D síncrono con reset asíncrono por flanco y entrada de habilitación de carga
module ffd(input wire clk, reset, d, carga, output reg q);

  always @(posedge clk, posedge reset)
    if (reset)
	    q <= 1'b0;
	  else
	    if (carga)
	      q <= d;

endmodule 

module  pila(input wire clk, reset, push, pop, input wire [9:0] inpush, output reg [9:0] outpop );
  reg [2:0] sp;
  //integer sp = 0;
  reg [9:0] mem[0:7];
  initial 
    begin
      sp = 0;
    end

    always @(push, pop, posedge reset) begin
	  if ( reset )
		sp = 3'b000;
	if ( push ) 
		begin
	        	mem[sp] = inpush;	
			sp = sp + 3'b001;
		end
	  if ( pop ) 
		begin
			sp = sp - 3'b001;
			outpop = mem[sp];
		end
	end

endmodule

//memoria de datos

module regprog (input wire clk, input wire we4, input wire [11:0] wra, input wire [7:0] wd, output wire [7:0] rd);
	
	// we4 : write enable
	// wra : write/read addres
	// wd : write data
	// rd : read data
	reg [7:0] regb[0:255];  //memoria de 255 de 8 bits de ancho

	initial
	begin
		$readmemb("regdata.dat", regb);
	end
	// sw -> 
	always @(posedge clk)
		if (we4) regb[wra[7:0]] <= wd;
	
	assign rd = regb[wra[11:4]];


endmodule


module mux41 #(parameter WIDTH = 8) (input wire [WIDTH-1:0] a, b, c, d, input wire [1:0] s, output reg [WIDTH-1:0] out);
	always@(a or b or c or d or s)
	begin
		case(s)
			2'b00: out <= a;
			2'b01: out <= b;
			2'b10: out <= c;
			2'b11: out <= d;
		endcase
	end
endmodule

cpu/alu.v
module alu(input wire [7:0] a, b,
           input wire [2:0] op_alu,
           output wire [7:0] y,
           output wire zero);

reg [7:0] s;		   
		   
always @(a, b, op_alu)
begin
  case (op_alu)              
    3'b000: s = a;
    3'b001: s = ~a;
    3'b010: s = a + b;
    3'b011: s = a - b;
    3'b100: s = a & b;
    3'b101: s = a | b;
    3'b110: s = -a;
    3'b111: s = -b;
	default: s = 'bx; //desconocido en cualquier otro caso (x ó z), por si se modifica el código
  endcase
end

assign y = s;

//Calculo del flag de cero
assign zero = ~(|y);   //operador de reducción |y hace la or de los bits del vector 'y' y devuelve 1 bit resultado
		   
endmodule

cpu/memprog.v
//Memoria de programa, se inicializa y no se modifica

module memprog(input  wire        clk,
               input  wire [9:0]  a,
               output wire [15:0] rd);

  reg [15:0] mem[0:1023]; //memoria de 1024 palabras de 16 bits de ancho

  initial
  begin
    $readmemb("progfile.dat",mem); // inicializa la memoria del fichero en texto binario
  end
  
  assign rd = mem[a];

endmodule

cpu/cd.v
module cd(input wire clk, reset, s_inc, we3, wez, s_pila, push, pop, we4, input wire [1:0] s_inm, input wire [2:0] op_alu, output wire z, output wire [5:0] opcode);
//Camino de datos de instrucciones de un solo ciclo
wire [9:0] mux_to_pc, pc_to_mem, sum_to_mux, mux_to_mux, pila_to_mux;
wire [7:0] rd1, rd2, alu_to_mux, wd3, memdat_to_mux;
wire [15:0] sal_mem_pro;
wire zalu;

//1
mux2 #10 mux_1(sal_mem_pro[9:0], sum_to_mux, s_inc, mux_to_mux);
//2
registro #10 pc(clk, reset, mux_to_pc, pc_to_mem);
//3
memprog mem_prog(clk, pc_to_mem, sal_mem_pro);
//4
regfile banco(clk, we3, sal_mem_pro[11:8], sal_mem_pro[7:4], sal_mem_pro[3:0], wd3, rd1, rd2);
//5
mux41 #8 mux_2(alu_to_mux, sal_mem_pro[11:4] ,memdat_to_mux, , s_inm, wd3);
//6
alu alu1(rd1, rd2, op_alu, alu_to_mux, zalu);
//7
ffd ffz(clk, reset, zalu, wez, z);
//8 
sum sum1(pc_to_mem, 10'b1 , sum_to_mux);
//9 
mux2 #10 mux_3(mux_to_mux, pila_to_mux, s_pila, mux_to_pc);
//10
pila pila1(clk, reset, push, pop, pc_to_mem, pila_to_mux);
//11
regprog regpro1(clk,we4,sal_mem_pro[11:0],rd1,memdat_to_mux);

assign opcode = sal_mem_pro[15:10];


endmodule

cpu/cpu.v
module cpu(input wire clk, reset);
//Procesador sin memoria de datos de un solo ciclo

wire s_inc, we3, wez, z, s_pila, push, pop, we4;
wire [5:0] opcode;
wire [2:0] op_alu;
wire [1:0] s_inm;

cd cd_1(clk, reset, s_inc, we3, wez, s_pila, push, pop, we4,  s_inm,  op_alu, z, opcode);
uc uc_1(opcode, z, s_inc, we3, wez, s_pila, push, pop, we4,  s_inm, op_alu);




endmodule

cpu/cpu_tb.v
`timescale 1 ns / 10 ps

// unidad de cuenta de simulacion / escala 
// frecuencia = 16'8 mhz

module cpu_tb;


reg clk, reset, ie1, ie2, ie3, ie4;
wire [7:0] o1, o2, o3, o4, i1, i2, i3, i4;

// generación de reloj clk
always //siempre activo, no hay condición de activación
begin
  clk = 1'b1;
  //#30;
  #20; // 50mhz
  clk = 1'b0;
  //#30;
  #20;
end

// instanciación del procesador
cpu micpu(clk, reset, ie1, ie2, ie3, ie4, o1, o2, o3, o4, i1, i2, i3, i4);

initial
begin
  $dumpfile("cpu_tb.vcd");
  //$dumpvars(0,cpu_tb.micpu.cd_1.banco.regb[0]); 
  $dumpvars;
  reset = 1;  //a partir del flanco de subida del reset empieza el funcionamiento normal
  #10;
  reset = 0;  //bajamos el reset 
  ie1 = 0;
  ie2 = 0;
  ie3 = 0;
  ie4 = 0;
end
/*
initial
begin
	#(2*60);
	ie1 = 1;
	#(60);
	ie1 = 0;
end
*/
initial
begin

  //#(9*60);  //Esperamos 9 ciclos o 9 instrucciones
  //#(9*40);  //Esperamos 9 ciclos o 9 instrucciones
  #(50001*40);  //Esperamos 9 ciclos o 9 instrucciones
  $finish;
end

endmodule

cpu/cpu_tb.vcd
$date
	Tue Mar 16 17:15:36 2021
$end
$version
	Icarus Verilog
$end
$timescale
	10ps
$end
$scope module cpu_tb $end
$var reg 1 ! clk $end
$var reg 1 " reset $end
$scope module micpu $end
$var wire 1 ! clk $end
$var wire 1 " reset $end
$var wire 1 # z $end
$var wire 1 $ wez $end
$var wire 1 % we4 $end
$var wire 1 & we3 $end
$var wire 1 ' s_pila $end
$var wire 2 ( s_inm [1:0] $end
$var wire 1 ) s_inc $end
$var wire 1 * push $end
$var wire 1 + pop $end
$var wire 6 , opcode [5:0] $end
$var wire 3 - op_alu [2:0] $end
$scope module cd_1 $end
$var wire 1 ! clk $end
$var wire 1 " reset $end
$var wire 1 . zalu $end
$var wire 1 # z $end
$var wire 1 $ wez $end
$var wire 1 % we4 $end
$var wire 1 & we3 $end
$var wire 8 / wd3 [7:0] $end
$var wire 10 0 sum_to_mux [9:0] $end
$var wire 16 1 sal_mem_pro [15:0] $end
$var wire 1 ' s_pila $end
$var wire 2 2 s_inm [1:0] $end
$var wire 1 ) s_inc $end
$var wire 8 3 rd2 [7:0] $end
$var wire 8 4 rd1 [7:0] $end
$var wire 1 * push $end
$var wire 1 + pop $end
$var wire 10 5 pila_to_mux [9:0] $end
$var wire 10 6 pc_to_mem [9:0] $end
$var wire 6 7 opcode [5:0] $end
$var wire 3 8 op_alu [2:0] $end
$var wire 10 9 mux_to_pc [9:0] $end
$var wire 10 : mux_to_mux [9:0] $end
$var wire 8 ; memdat_to_mux [7:0] $end
$var wire 8 < alu_to_mux [7:0] $end
$scope module alu1 $end
$var wire 8 = y [7:0] $end
$var wire 1 . zero $end
$var wire 3 > op_alu [2:0] $end
$var wire 8 ? b [7:0] $end
$var wire 8 @ a [7:0] $end
$var reg 8 A s [7:0] $end
$upscope $end
$scope module banco $end
$var wire 1 ! clk $end
$var wire 4 B ra1 [3:0] $end
$var wire 4 C ra2 [3:0] $end
$var wire 4 D wa3 [3:0] $end
$var wire 1 & we3 $end
$var wire 8 E wd3 [7:0] $end
$var wire 8 F rd2 [7:0] $end
$var wire 8 G rd1 [7:0] $end
$upscope $end
$scope module ffz $end
$var wire 1 ! clk $end
$var wire 1 . d $end
$var wire 1 " reset $end
$var wire 1 $ carga $end
$var reg 1 # q $end
$upscope $end
$scope module mem_prog $end
$var wire 1 ! clk $end
$var wire 16 H rd [15:0] $end
$var wire 10 I a [9:0] $end
$upscope $end
$scope module mux_1 $end
$var wire 10 J d0 [9:0] $end
$var wire 10 K y [9:0] $end
$var wire 1 ) s $end
$var wire 10 L d1 [9:0] $end
$upscope $end
$scope module mux_2 $end
$var wire 8 M a [7:0] $end
$var wire 8 N b [7:0] $end
$var wire 8 O d [7:0] $end
$var wire 2 P s [1:0] $end
$var wire 8 Q c [7:0] $end
$var reg 8 R out [7:0] $end
$upscope $end
$scope module mux_3 $end
$var wire 10 S d0 [9:0] $end
$var wire 10 T y [9:0] $end
$var wire 1 ' s $end
$var wire 10 U d1 [9:0] $end
$upscope $end
$scope module pc $end
$var wire 1 ! clk $end
$var wire 10 V d [9:0] $end
$var wire 1 " reset $end
$var reg 10 W q [9:0] $end
$upscope $end
$scope module pila1 $end
$var wire 1 ! clk $end
$var wire 10 X inpush [9:0] $end
$var wire 1 " reset $end
$var wire 1 * push $end
$var wire 1 + pop $end
$var reg 10 Y outpop [9:0] $end
$var reg 3 Z sp [2:0] $end
$upscope $end
$scope module regpro1 $end
$var wire 1 ! clk $end
$var wire 8 [ rd [7:0] $end
$var wire 8 \ wd [7:0] $end
$var wire 12 ] wra [11:0] $end
$var wire 1 % we4 $end
$upscope $end
$scope module sum1 $end
$var wire 10 ^ a [9:0] $end
$var wire 10 _ b [9:0] $end
$var wire 10 ` y [9:0] $end
$upscope $end
$upscope $end
$scope module uc_1 $end
$var wire 6 a opcode [5:0] $end
$var wire 1 # z $end
$var reg 3 b op_alu [2:0] $end
$var reg 1 + pop $end
$var reg 1 * push $end
$var reg 1 ) s_inc $end
$var reg 2 c s_inm [1:0] $end
$var reg 1 ' s_pila $end
$var reg 1 & we3 $end
$var reg 1 % we4 $end
$var reg 1 $ wez $end
$upscope $end
$upscope $end
$upscope $end
$enddefinitions $end
#0
$dumpvars
b10 c
bx b
b111000 a
b1 `
b1 _
b0 ^
b100010 ]
b0 \
b1010 [
b0 Z
bx Y
b0 X
b0 W
b1 V
bx U
b1 T
b1 S
b1010 R
b1010 Q
b10 P
bz O
b10 N
bx M
b1 L
b1 K
b100010 J
b0 I
b1110000000100010 H
b0 G
b0 F
b1010 E
b10 D
b10 C
b0 B
bx A
b0 @
b0 ?
bx >
bx =
bx <
b1010 ;
b1 :
b1 9
bx 8
b111000 7
b0 6
bx 5
b0 4
b0 3
b10 2
b1110000000100010 1
b1 0
b1010 /
x.
bx -
b111000 ,
x+
x*
1)
b10 (
0'
1&
0%
0$
0#
1"
1!
$end
#1000
0"
#3000
0!
#6000
b10100 /
b10100 E
b10100 R
0.
b10100 <
b10100 =
b10100 A
b10100 M
b10 9
b10 T
b10 V
0+
0*
b0 (
b0 2
b0 P
b0 c
1$
b10 -
b10 8
b10 >
b10 b
b0 ;
b0 Q
b0 [
b1010 4
b1010 @
b1010 G
b1010 \
b1010 3
b1010 ?
b1010 F
b10 :
b10 K
b10 S
b1000 ,
b1000 7
b1000 a
b1000110100 ]
b100011 N
b100 D
b11 C
b10 B
b1000110100 J
b10 0
b10 L
b10 `
b10001000110100 1
b10001000110100 H
b1 6
b1 I
b1 W
b1 X
b1 ^
1!
#9000
0!
#12000
b11 9
b11 T
b11 V
b0 3
b0 ?
b0 F
b10100 4
b10100 @
b10100 G
b10100 \
b11 :
b11 K
b11 S
b111101 ,
b111101 7
b111101 a
b10000000100 ]
b1000000 N
b0 C
b100 B
b100 J
b11 0
b11 L
b11 `
b1111010000000100 1
b1111010000000100 H
b10 6
b10 I
b10 W
b10 X
b10 ^
1!
#15000
0!
#18000
b0 /
b0 E
b0 R
1.
b0 <
b0 =
b0 A
b0 M
b100 9
b100 T
b100 V
b0 -
b0 8
b0 >
b0 b
b0 4
b0 @
b0 G
b0 \
b100 :
b100 K
b100 S
b0 ,
b0 7
b0 a
b0 ]
b0 N
b0 D
b0 B
b0 J
b100 0
b100 L
b100 `
b0 1
b0 H
b11 6
b11 I
b11 W
b11 X
b11 ^
1!
#21000
0!
#24000
b101 9
b101 T
b101 V
b101 :
b101 K
b101 S
b101 0
b101 L
b101 `
b100 6
b100 I
b100 W
b100 X
b100 ^
1#
1!
#27000
0!
#30000
b110 9
b110 T
b110 V
b110 :
b110 K
b110 S
b110 0
b110 L
b110 `
b101 6
b101 I
b101 W
b101 X
b101 ^
1!
#33000
0!
#36000
b111 9
b111 T
b111 V
b111 :
b111 K
b111 S
b111 0
b111 L
b111 `
b110 6
b110 I
b110 W
b110 X
b110 ^
1!
#39000
0!
#42000
b1000 9
b1000 T
b1000 V
b1000 :
b1000 K
b1000 S
b1000 0
b1000 L
b1000 `
b111 6
b111 I
b111 W
b111 X
b111 ^
1!
#45000
0!
#48000
b1001 9
b1001 T
b1001 V
b1001 :
b1001 K
b1001 S
b1001 0
b1001 L
b1001 `
b1000 6
b1000 I
b1000 W
b1000 X
b1000 ^
1!
#51000
0!
#54000
b1010 9
b1010 T
b1010 V
b1010 :
b1010 K
b1010 S
b1010 0
b1010 L
b1010 `
b1001 6
b1001 I
b1001 W
b1001 X
b1001 ^
1!
