cpu/uc.v
module uc(input wire [15:0] opcode, input wire z, output reg s_inc, we3, wez, s_pila, push, pop, we4, s_out, we5, we6, we7, we8,  output reg [1:0] s_port ,output reg [1:0] s_inm,  output reg [2:0] op_alu);

always @(opcode)
casez (opcode[15:10])
	6'b0zzzzz:   // aritmetica
		begin
			op_alu = opcode[14:12];
			s_inc = 1;
			s_inm = 2'b00;
			s_pila = 0; 
			we3 = 1; 
			push = 0;
			pop = 0; 
			we4 = 0;
			we5 = 0;
			we6 = 0;
			we7 = 0;
			we8 = 0;
			wez = 1;
		        s_port = 2'b00;
			s_out = 0;	
		end
	6'b100000:   // carga inmediata
		begin
			op_alu = 3'b000;
			s_inm = 2'b01; 
			we3 = 1;
			s_inc = 1; 
			s_pila = 0;
			push = 0; 
			pop = 0;
			we4 = 0;
			we5 = 0;
			we6 = 0;
			we7 = 0;
			we8 = 0;
			s_out = 0;
			s_port = 2'b00;
			wez = 0;

		end
	6'b100001:  // salto
		begin
			s_inc = 0; 
			s_pila = 0;
			push = 0; 
			pop = 0;
			we3 = 0;
			we4 = 0;
			we5 = 0;
			we6 = 0;
			we7 = 0;
			we8 = 0;
			wez = 0;
			s_out = 0;
			s_port = 2'b00;
			op_alu = 3'b00;
			s_inm = 2'b00;
		end
	6'b100010:  // salto si z
		begin
			s_pila = 0; 
			we3 = 0;
		        we4 = 0;
			we5 = 0;
			we6 = 0;
			we7 = 0;
			we8 = 0;	
			wez = 0;
			push = 0; 
			pop = 0;
			s_port = 2'b00;
			s_inm = 2'b00;
			s_out = 0;
			op_alu = 3'b000;
			// if ( z == 1b'1 ) begin
			if ( z == 1 ) begin
				s_inc = 0;
			end else begin
				s_inc = 1;
			end
		end
	6'b100011: // salto si no z
		begin
		       	we3 = 0;
			we4 = 0;
		       	we5 = 0;
			we6 = 0;
			we7 = 0;
			we8 = 0;
			wez = 0;
			push = 0; 
			pop = 0;
			s_pila = 0;
			s_port = 2'b00;
			s_inm = 2'b00;
			s_out = 0;
			op_alu = 3'b000;
			if ( z == 0 ) begin
				s_inc = 0;
			end else begin
				s_inc = 1;
			end
		end
	6'b100100: // push pila
		begin
			push = 1; 
			pop = 0;
			we3 = 0; 
			we4 = 0;
			we5 = 0;
			we6 = 0;
			we7 = 0;
			we8 = 0;
			wez = 0;
			s_pila = 0;
			s_port = 2'b00;
			s_out = 0;
			s_inc = 1;
			s_inm = 2'b00;
			op_alu = 3'b000;
		end
	6'b100101: // pop pila
		begin
			pop = 1; 
			push = 0;
			we3 = 0; 
			we4 = 0;
			we5 = 0;
			we6 = 0;
			we7 = 0;
			we8 = 0;
			wez = 0;
			s_pila = 1;
			s_port = 2'b00;
			s_out = 0;
			s_inc = 1;
			s_inm = 2'b00;
			op_alu = 3'b000;
		end
	6'b100110: // input to reg  100110 empty[4] s_port[2] dir reg[4]
		begin
			push = 0; 
			pop = 0;
			we3 = 1; 
			we4 = 0;
			we5 = 0;
			we6 = 0;
			we7 = 0;
			we8 = 0;
			wez = 0; 
			s_pila = 0; 
			s_port = opcode[5:4]; 
			s_out = 0;
			s_inc = 1;
			s_inm = 2'b11;
			op_alu = 3'b000;

		end
	6'b100111: // reg to output  100111 reg[11:8] empty[7:2] port_out[1:0] 
		begin
			push = 0; 
			pop = 0;
		       	we3 = 0;	
			we4 = 0;
			we5 = -opcode[0] & -opcode[1];
			we6 = -opcode[0] & opcode[1];
			we7 = opcode[0] & -opcode[1];
			we8 = opcode[0] & opcode[1];
			wez = 0;
			s_pila = 0;
			s_port = 2'b00;
			s_out = 0;
			s_inc = 1;
			s_inm = 2'b00;
			op_alu = 3'b000;
		end
	6'b101000: // mem prog to out (salida inmediato) 101000 inmediato[9:2] port_out[1:0]
		begin
			push = 0; 
			pop = 0;
			we4 = 0;
			we3 = 0;
			we5 = -opcode[0] & -opcode[1];
			we6 = -opcode[0] & -opcode[1];
			we7 = -opcode[0] & -opcode[1];
			we8 = -opcode[0] & -opcode[1];
			wez = 0;
			s_pila = 0;
			s_port = 2'b00;
			s_out = 1;
			s_inc = 1;
			s_inm = 2'b00;
			op_alu = 3'b000;

		end
	6'b111000: // load word (mem datos ----> banco registros)  1110 mem dato[8] banc[4]
		begin
		        push = 0; 
			pop = 0;	
			we3 = 1; 
			we4 = 0;
		       	we5 = 0;
			we6 = 0;
			we7 = 0;
			we8 = 0;	
			wez = 0;
			s_pila = 0;
			s_port = 2'b00;
			s_out = 0;
			s_inc = 1; 
			s_inm = 2'b10;
			op_alu = 3'b000;
		end
	6'b1111zz: // save word (banco registros ----> mem datos)  1111 banc[4] mem dato[8]
		begin
			s_inc = 1; 
			push = 0; 
			pop = 0;
			we3 = 0; 
			we4 = 1;
		       	we5 = 0;
			we6 = 0;
			we7 = 0;
			we8 = 0;	
			wez = 0;
			s_pila = 0;
			s_port = 2'b00;
			s_out = 0;
			s_inc = 1;
			s_inm = 2'b00;
			op_alu = 3'b000;
		end

default:  ;
endcase

endmodule

cpu/componentes.v
//Componentes varios

//Banco de registros de dos salidas y una entrada
module regfile(input  wire        clk, 
               input  wire        we3,           //señal de habilitación de escritura
               input  wire [3:0]  ra1, ra2, wa3, //direcciones de regs leidos y reg a escribir
               input  wire [7:0]  wd3, 			 //dato a escribir
               output wire [7:0]  rd1, rd2);     //datos leidos

  reg [7:0] regb[0:15]; //memoria de 16 registros de 8 bits de ancho

  initial
  begin
    $readmemb("regfile.dat",regb); // inicializa los registros a valores conocidos
  end  
  
  // El registro 0 siempre es cero
  // se leen dos reg combinacionalmente
  // y la escritura del tercero ocurre en flanco de subida del reloj
  
  always @(posedge clk)
    if (we3) regb[wa3] <= wd3;	
  
  assign rd1 = (ra1 != 0) ? regb[ra1] : 0;
  assign rd2 = (ra2 != 0) ? regb[ra2] : 0;

endmodule

//modulo sumador  
module sum(input  wire [9:0] a, b,
             output wire [9:0] y);

  assign y = a + b;

endmodule

//modulo registro para modelar el PC, cambia en cada flanco de subida de reloj o de reset
module registro #(parameter WIDTH = 8)
              (input wire             clk, reset,
               input wire [WIDTH-1:0] d, 
               output reg [WIDTH-1:0] q);

  always @(posedge clk, posedge reset)
    if (reset) q <= 0;
    else       q <= d;

endmodule

//modulo multiplexor, si s=1 sale d1, s=0 sale d0
module mux2 #(parameter WIDTH = 8)
             (input  wire [WIDTH-1:0] d0, d1, 
              input  wire             s, 
              output wire [WIDTH-1:0] y);

  assign y = s ? d1 : d0; 

endmodule

//Biestable para el flag de cero
//Biestable tipo D síncrono con reset asíncrono por flanco y entrada de habilitación de carga
module ffd(input wire clk, reset, d, carga, output reg q);

  always @(posedge clk, posedge reset)
    if (reset)
	    q <= 1'b0;
	  else
	    if (carga)
	      q <= d;

endmodule 

module  pila(input wire clk, reset, push, pop, input wire [9:0] inpush, output reg [9:0] outpop );
  reg [2:0] sp;
  //integer sp = 0;
  reg [9:0] mem[0:7];
  initial 
    begin
      sp = 0;
    end

    always @(push, pop, posedge reset) begin
	if ( reset )
		sp = 3'b000;
	if ( push ) 
		begin
	        	mem[sp] = inpush;	
			sp = sp + 3'b001;
			outpop = 3'b000;
		end
	  if ( pop ) 
		begin
			sp = sp - 3'b001;
			outpop = mem[sp];
		end
	end

endmodule

//memoria de datos

module regprog (input wire clk, input wire we4, input wire [11:0] wra, input wire [7:0] wd, output wire [7:0] rd);
	
	// we4 : write enable
	// wra : write/read addres
	// wd : write data
	// rd : read data
	reg [7:0] regb[0:255];  //memoria de 255 de 8 bits de ancho

	initial
	begin
		$readmemb("regdata.dat", regb);
	end
	// sw -> 
	always @(posedge clk)
		if (we4) regb[wra[7:0]] <= wd;
	
	assign rd = regb[wra[11:4]];


endmodule

module mux41 #(parameter WIDTH = 8) (input wire [WIDTH-1:0] a, b, c, d, input wire [1:0] s, output reg [WIDTH-1:0] out);
	always@(a or b or c or d or s)
	begin
		case(s)
			2'b00: out <= a;
			2'b01: out <= b;
			2'b10: out <= c;
			2'b11: out <= d;
		endcase
	end
endmodule

cpu/alu.v
module alu(input wire [7:0] a, b,
           input wire [2:0] op_alu,
           output wire [7:0] y,
           output wire zero);

reg [7:0] s;		   
		   
always @(a, b, op_alu)
begin
  case (op_alu)              
    3'b000: s = a;
    3'b001: s = ~a;
    3'b010: s = a + b;
    3'b011: s = a - b;
    3'b100: s = a & b;
    3'b101: s = a | b;
    3'b110: s = -a;
    3'b111: s = -b;
	default: s = 'bx; //desconocido en cualquier otro caso (x ó z), por si se modifica el código
  endcase
end

assign y = s;

//Calculo del flag de cero
assign zero = ~(|y);   //operador de reducción |y hace la or de los bits del vector 'y' y devuelve 1 bit resultado
		   
endmodule

cpu/memprog.v
//Memoria de programa, se inicializa y no se modifica

module memprog(input  wire        clk,
               input  wire [9:0]  a,
               output wire [15:0] rd);

  reg [15:0] mem[0:1023]; //memoria de 1024 palabras de 16 bits de ancho

  initial
  begin
    $readmemb("progfile.dat",mem); // inicializa la memoria del fichero en texto binario
  end
  
  assign rd = mem[a];

endmodule

cpu/cd.v
module cd(input wire clk, reset, s_inc, we3, wez, s_pila, push, pop, we4, s_out, we5, we6, we7, we8,  input wire [1:0] s_port, input wire [1:0] s_inm, input wire [2:0] op_alu, output wire z, output wire [15:0] opcode, output wire [7:0] reg1_out, reg2_out, reg3_out, reg4_out, input wire [7:0] i1, i2, i3, i4);
//Camino de datos de instrucciones de un solo ciclo
wire [9:0] mux_to_pc, pc_to_mem, sum_to_mux, mux_to_mux, pila_to_mux;
wire [7:0] rd1, rd2, alu_to_mux, wd3, memdat_to_mux, mux_to_reg, input_mux_to_mux;
wire [15:0] sal_mem_pro;
wire zalu;

//1
mux2 #10 mux_1(sal_mem_pro[9:0], sum_to_mux, s_inc, mux_to_mux);
//2
registro #10 pc(clk, reset, mux_to_pc, pc_to_mem);
//3
memprog mem_prog(clk, pc_to_mem, sal_mem_pro);
//4
regfile banco(clk, we3, sal_mem_pro[11:8], sal_mem_pro[7:4], sal_mem_pro[3:0], wd3, rd1, rd2);
//5
mux41 #8 mux_2(alu_to_mux, sal_mem_pro[11:4] ,memdat_to_mux, , s_inm, wd3);
//6
alu alu1(rd1, rd2, op_alu, alu_to_mux, zalu);
//7
ffd ffz(clk, reset, zalu, wez, z);
//8 
sum sum1(pc_to_mem, 10'b1 , sum_to_mux);
//9 
mux2 #10 mux_3(mux_to_mux, pila_to_mux, s_pila, mux_to_pc);
//10
pila pila1(clk, reset, push, pop, pc_to_mem, pila_to_mux);
//11
regprog regpro1(clk,we4,sal_mem_pro[11:0],rd1,memdat_to_mux);
//12
mux41 #8 mux_4(i1,i2,i3,i4,s_port,input_mux_to_mux);
//13
mux2 #8 mux_5(rd1,sal_mem_pro[9:2],s_out,mux_to_reg);
//14
registro #8 reg1(we5,reset,mux_to_reg,reg1_out); 
//15
registro #8 reg2(we6,reset,mux_to_reg,reg2_out);
//16
registro #8 reg3(we7,reset,mux_to_reg,reg3_out); 
//17
registro #8 reg4(we8,reset,mux_to_reg,reg4_out); 


assign opcode = sal_mem_pro;


endmodule

cpu/cpu.v
module cpu(input wire clk, reset, output wire [7:0] reg1_out, reg2_out, reg3_out, reg4_out, input wire [7:0] i1, i2, i3, i4);
//Procesador sin memoria de datos de un solo ciclo

wire s_inc, we3, wez, z, s_pila, push, pop, we4, s_out, we5, we6, we7, we8;
wire [15:0] opcode;
wire [2:0] op_alu;
wire [1:0] s_inm; 
wire [1:0] s_port;

cd cd_1(clk, reset, s_inc, we3, wez, s_pila, push, pop, we4, s_out, we5, we6, we7, we8, s_port, s_inm,  op_alu, z, opcode, reg1_out, reg2_out, reg3_out, reg4_out, i1, i2, i3, i4);
uc uc_1(opcode, z, s_inc, we3, wez, s_pila, push, pop, we4, s_out, we5, we6, we7, we8, s_port,  s_inm, op_alu);




endmodule

cpu/cpu_tb.v
`timescale 1 ns / 10 ps

module cpu_tb;


reg clk, reset;
wire [7:0] o1, o2, o3, o4, i1, i2, i3, i4;


// generación de reloj clk
always //siempre activo, no hay condición de activación
begin
  clk = 1'b1;
  #30;
  clk = 1'b0;
  #30;
end

// instanciación del procesador
cpu micpu(clk, reset, o1, o2, o3, o4, i1, i2, i3, i4);

initial
begin
  $dumpfile("cpu_tb.vcd");
  //$dumpvars(0,cpu_tb.micpu.cd_1.banco.regb[); TODO
  $dumpvars;
  reset = 1;  //a partir del flanco de subida del reset empieza el funcionamiento normal
  #10;
  reset = 0;  //bajamos el reset 
end

initial
begin

  #(9*60);  //Esperamos 9 ciclos o 9 instrucciones
  $finish;
end

endmodule

cpu/cpu_tb.vcd
$date
	Wed Mar 17 21:33:43 2021
$end
$version
	Icarus Verilog
$end
$timescale
	10ps
$end
$scope module cpu_tb $end
$var wire 8 ! i1 [7:0] $end
$var wire 8 " i2 [7:0] $end
$var wire 8 # i3 [7:0] $end
$var wire 8 $ i4 [7:0] $end
$var wire 8 % o4 [7:0] $end
$var wire 8 & o3 [7:0] $end
$var wire 8 ' o2 [7:0] $end
$var wire 8 ( o1 [7:0] $end
$var reg 1 ) clk $end
$var reg 1 * reset $end
$scope module micpu $end
$var wire 1 ) clk $end
$var wire 8 + i1 [7:0] $end
$var wire 8 , i2 [7:0] $end
$var wire 8 - i3 [7:0] $end
$var wire 8 . i4 [7:0] $end
$var wire 1 * reset $end
$var wire 1 / z $end
$var wire 1 0 wez $end
$var wire 1 1 we8 $end
$var wire 1 2 we7 $end
$var wire 1 3 we6 $end
$var wire 1 4 we5 $end
$var wire 1 5 we4 $end
$var wire 1 6 we3 $end
$var wire 2 7 s_port [1:0] $end
$var wire 1 8 s_pila $end
$var wire 1 9 s_out $end
$var wire 2 : s_inm [1:0] $end
$var wire 1 ; s_inc $end
$var wire 8 < reg4_out [7:0] $end
$var wire 8 = reg3_out [7:0] $end
$var wire 8 > reg2_out [7:0] $end
$var wire 8 ? reg1_out [7:0] $end
$var wire 1 @ push $end
$var wire 1 A pop $end
$var wire 16 B opcode [15:0] $end
$var wire 3 C op_alu [2:0] $end
$scope module cd_1 $end
$var wire 1 ) clk $end
$var wire 8 D i1 [7:0] $end
$var wire 8 E i2 [7:0] $end
$var wire 8 F i3 [7:0] $end
$var wire 8 G i4 [7:0] $end
$var wire 16 H opcode [15:0] $end
$var wire 1 * reset $end
$var wire 1 I zalu $end
$var wire 1 / z $end
$var wire 1 0 wez $end
$var wire 1 1 we8 $end
$var wire 1 2 we7 $end
$var wire 1 3 we6 $end
$var wire 1 4 we5 $end
$var wire 1 5 we4 $end
$var wire 1 6 we3 $end
$var wire 8 J wd3 [7:0] $end
$var wire 10 K sum_to_mux [9:0] $end
$var wire 16 L sal_mem_pro [15:0] $end
$var wire 2 M s_port [1:0] $end
$var wire 1 8 s_pila $end
$var wire 1 9 s_out $end
$var wire 2 N s_inm [1:0] $end
$var wire 1 ; s_inc $end
$var wire 8 O reg4_out [7:0] $end
$var wire 8 P reg3_out [7:0] $end
$var wire 8 Q reg2_out [7:0] $end
$var wire 8 R reg1_out [7:0] $end
$var wire 8 S rd2 [7:0] $end
$var wire 8 T rd1 [7:0] $end
$var wire 1 @ push $end
$var wire 1 A pop $end
$var wire 10 U pila_to_mux [9:0] $end
$var wire 10 V pc_to_mem [9:0] $end
$var wire 3 W op_alu [2:0] $end
$var wire 8 X mux_to_reg [7:0] $end
$var wire 10 Y mux_to_pc [9:0] $end
$var wire 10 Z mux_to_mux [9:0] $end
$var wire 8 [ memdat_to_mux [7:0] $end
$var wire 8 \ input_mux_to_mux [7:0] $end
$var wire 8 ] alu_to_mux [7:0] $end
$scope module alu1 $end
$var wire 8 ^ y [7:0] $end
$var wire 1 I zero $end
$var wire 3 _ op_alu [2:0] $end
$var wire 8 ` b [7:0] $end
$var wire 8 a a [7:0] $end
$var reg 8 b s [7:0] $end
$upscope $end
$scope module banco $end
$var wire 1 ) clk $end
$var wire 4 c ra1 [3:0] $end
$var wire 4 d ra2 [3:0] $end
$var wire 4 e wa3 [3:0] $end
$var wire 1 6 we3 $end
$var wire 8 f wd3 [7:0] $end
$var wire 8 g rd2 [7:0] $end
$var wire 8 h rd1 [7:0] $end
$upscope $end
$scope module ffz $end
$var wire 1 ) clk $end
$var wire 1 I d $end
$var wire 1 * reset $end
$var wire 1 0 carga $end
$var reg 1 / q $end
$upscope $end
$scope module mem_prog $end
$var wire 1 ) clk $end
$var wire 16 i rd [15:0] $end
$var wire 10 j a [9:0] $end
$upscope $end
$scope module mux_1 $end
$var wire 10 k d0 [9:0] $end
$var wire 10 l y [9:0] $end
$var wire 1 ; s $end
$var wire 10 m d1 [9:0] $end
$upscope $end
$scope module mux_2 $end
$var wire 8 n a [7:0] $end
$var wire 8 o b [7:0] $end
$var wire 8 p d [7:0] $end
$var wire 2 q s [1:0] $end
$var wire 8 r c [7:0] $end
$var reg 8 s out [7:0] $end
$upscope $end
$scope module mux_3 $end
$var wire 10 t d0 [9:0] $end
$var wire 10 u y [9:0] $end
$var wire 1 8 s $end
$var wire 10 v d1 [9:0] $end
$upscope $end
$scope module mux_4 $end
$var wire 8 w a [7:0] $end
$var wire 8 x b [7:0] $end
$var wire 8 y c [7:0] $end
$var wire 8 z d [7:0] $end
$var wire 2 { s [1:0] $end
$var reg 8 | out [7:0] $end
$upscope $end
$scope module mux_5 $end
$var wire 8 } d0 [7:0] $end
$var wire 8 ~ d1 [7:0] $end
$var wire 8 !" y [7:0] $end
$var wire 1 9 s $end
$upscope $end
$scope module pc $end
$var wire 1 ) clk $end
$var wire 10 "" d [9:0] $end
$var wire 1 * reset $end
$var reg 10 #" q [9:0] $end
$upscope $end
$scope module pila1 $end
$var wire 1 ) clk $end
$var wire 10 $" inpush [9:0] $end
$var wire 1 * reset $end
$var wire 1 @ push $end
$var wire 1 A pop $end
$var reg 10 %" outpop [9:0] $end
$var reg 3 &" sp [2:0] $end
$upscope $end
$scope module reg1 $end
$var wire 8 '" d [7:0] $end
$var wire 1 * reset $end
$var wire 1 4 clk $end
$var reg 8 (" q [7:0] $end
$upscope $end
$scope module reg2 $end
$var wire 8 )" d [7:0] $end
$var wire 1 * reset $end
$var wire 1 3 clk $end
$var reg 8 *" q [7:0] $end
$upscope $end
$scope module reg3 $end
$var wire 8 +" d [7:0] $end
$var wire 1 * reset $end
$var wire 1 2 clk $end
$var reg 8 ," q [7:0] $end
$upscope $end
$scope module reg4 $end
$var wire 8 -" d [7:0] $end
$var wire 1 * reset $end
$var wire 1 1 clk $end
$var reg 8 ." q [7:0] $end
$upscope $end
$scope module regpro1 $end
$var wire 1 ) clk $end
$var wire 8 /" rd [7:0] $end
$var wire 8 0" wd [7:0] $end
$var wire 12 1" wra [11:0] $end
$var wire 1 5 we4 $end
$upscope $end
$scope module sum1 $end
$var wire 10 2" a [9:0] $end
$var wire 10 3" b [9:0] $end
$var wire 10 4" y [9:0] $end
$upscope $end
$upscope $end
$scope module uc_1 $end
$var wire 16 5" opcode [15:0] $end
$var wire 1 / z $end
$var reg 3 6" op_alu [2:0] $end
$var reg 1 A pop $end
$var reg 1 @ push $end
$var reg 1 ; s_inc $end
$var reg 2 7" s_inm [1:0] $end
$var reg 1 9 s_out $end
$var reg 1 8 s_pila $end
$var reg 2 8" s_port [1:0] $end
$var reg 1 6 we3 $end
$var reg 1 5 we4 $end
$var reg 1 4 we5 $end
$var reg 1 3 we6 $end
$var reg 1 2 we7 $end
$var reg 1 1 we8 $end
$var reg 1 0 wez $end
$upscope $end
$upscope $end
$upscope $end
$enddefinitions $end
#0
$dumpvars
b0 8"
b0 7"
b10 6"
b10000100100011 5"
b1 4"
b1 3"
b0 2"
b100100011 1"
b10 0"
b0 /"
b0 ."
b10 -"
b0 ,"
b10 +"
b0 *"
b10 )"
b0 ("
b10 '"
b0 &"
bx %"
b0 $"
b0 #"
b1 ""
b10 !"
b1001000 ~
b10 }
bz |
b0 {
bz z
bz y
bz x
bz w
bx v
b1 u
b1 t
b1000 s
b0 r
b0 q
bz p
b10010 o
b1000 n
b1 m
b1 l
b100100011 k
b0 j
b10000100100011 i
b10 h
b110 g
b1000 f
b11 e
b10 d
b1 c
b1000 b
b10 a
b110 `
b10 _
b1000 ^
b1000 ]
bz \
b0 [
b1 Z
b1 Y
b10 X
b10 W
b0 V
bx U
b10 T
b110 S
b0 R
b0 Q
b0 P
b0 O
b0 N
b0 M
b10000100100011 L
b1 K
b1000 J
0I
b10000100100011 H
bz G
bz F
bz E
bz D
b10 C
b10000100100011 B
0A
0@
b0 ?
b0 >
b0 =
b0 <
1;
b0 :
09
08
b0 7
16
05
04
03
02
01
10
0/
bz .
bz -
bz ,
bz +
1*
1)
b0 (
b0 '
b0 &
b0 %
bz $
bz #
bz "
bz !
$end
#1000
0*
#3000
0)
#6000
b0 J
b0 f
b0 s
1I
b0 X
b0 !"
b0 '"
b0 )"
b0 +"
b0 -"
b10 Y
b10 u
b10 ""
b0 S
b0 `
b0 g
b0 T
b0 a
b0 h
b0 }
b0 0"
b0 ]
b0 ^
b0 b
b0 n
b10 Z
b10 l
b10 t
b0 ~
b0 1"
b0 o
b0 e
b0 d
b0 c
b0 k
b0 C
b0 W
b0 _
b0 6"
b10 K
b10 m
b10 4"
b0 B
b0 H
b0 5"
b0 L
b0 i
b1 V
b1 j
b1 #"
b1 $"
b1 2"
1)
#9000
0)
#12000
b11 Y
b11 u
b11 ""
b11 Z
b11 l
b11 t
b11 K
b11 m
b11 4"
b10 V
b10 j
b10 #"
b10 $"
b10 2"
1/
1)
#15000
0)
#18000
b100 Y
b100 u
b100 ""
b100 Z
b100 l
b100 t
b100 K
b100 m
b100 4"
b11 V
b11 j
b11 #"
b11 $"
b11 2"
1)
#21000
0)
#24000
b101 Y
b101 u
b101 ""
b101 Z
b101 l
b101 t
b101 K
b101 m
b101 4"
b100 V
b100 j
b100 #"
b100 $"
b100 2"
1)
#27000
0)
#30000
b110 Y
b110 u
b110 ""
b110 Z
b110 l
b110 t
b110 K
b110 m
b110 4"
b101 V
b101 j
b101 #"
b101 $"
b101 2"
1)
#33000
0)
#36000
b111 Y
b111 u
b111 ""
b111 Z
b111 l
b111 t
b111 K
b111 m
b111 4"
b110 V
b110 j
b110 #"
b110 $"
b110 2"
1)
#39000
0)
#42000
b1000 Y
b1000 u
b1000 ""
b1000 Z
b1000 l
b1000 t
b1000 K
b1000 m
b1000 4"
b111 V
b111 j
b111 #"
b111 $"
b111 2"
1)
#45000
0)
#48000
b1001 Y
b1001 u
b1001 ""
b1001 Z
b1001 l
b1001 t
b1001 K
b1001 m
b1001 4"
b1000 V
b1000 j
b1000 #"
b1000 $"
b1000 2"
1)
#51000
0)
#54000
b1010 Y
b1010 u
b1010 ""
b1010 Z
b1010 l
b1010 t
b1010 K
b1010 m
b1010 4"
b1001 V
b1001 j
b1001 #"
b1001 $"
b1001 2"
1)
