componentes.v
`timescale 1 ns / 10 ps


// Registro de 4 bits, soporta Carga de entrada, reseteo y desplazamiento aritmético o lógico
// La línea de Carga indica que se va a asignar un nuevo valor al registro que viene por "entrada"
// La línea de Desplaza indica que se va a desplazar el contenido del registro. El bit más significativo se completa con la entrada "bit_en_desp"
module registro4 (input wire [3:0] entrada, input wire bit_en_desp, input wire Carga, Desplaza, clk, reset, output wire [3:0] salida);
  wire enable;

  assign enable = Carga | Desplaza; //Si se carga o desplaza se habilitan en modificación los biestables

  cdaff ff0(Carga, entrada[0], salida[1], clk, reset, enable, salida[0]);
  cdaff ff1(Carga, entrada[1], salida[2], clk, reset, enable, salida[1]);
  cdaff ff2(Carga, entrada[2], salida[3], clk, reset, enable, salida[2]);
  cdaff ff3(Carga, entrada[3], bit_en_desp, clk, reset, enable, salida[3]); //entra un bit en el desplaz
endmodule

// Registro de 3 bits, soporta Carga de entrada, reseteo y desplazamiento aritmético o lógico
// La línea de Carga indica que se va a asignar un nuevo valor al registro que viene por "entrada"
// La línea de Desplaza indica que se va a desplazar el contenido del registro. El bit más significativo se completa con la entrada "bit_en_desp"
module registro3 (input wire [2:0] entrada, input wire bit_en_desp, input wire Carga, Desplaza, clk, reset, output wire [2:0] salida);
  wire enable;
  
  assign enable = Carga | Desplaza; //Si se carga o desplaza se habilitan en modificación los biestables

  cdaff ff0(Carga, entrada[0], salida[1], clk, reset, enable, salida[0]);
  cdaff ff1(Carga, entrada[1], salida[2], clk, reset, enable, salida[1]);
  cdaff ff2(Carga, entrada[2], bit_en_desp, clk, reset, enable, salida[2]); //entra un bit en el desplaz
endmodule

//Biestable con entrada de mux para aceptar dos entradas posibles
module cdaff (input wire selc_d, inp_c, inp_d, clk, reset, carga, output wire salida);
  wire inp;
  
  ffdc ff0(clk, reset, carga, inp, salida);
  mux2_1_i1 mux0(inp, inp_d, inp_c, selc_d);
endmodule

//Mux de dos entradas de 1 bit realizado a partir de puertas 
module mux2_1_i1(output wire out, input wire a, b, s);
  //Declaración de conexiones internas
  wire  s_n, sa, sb;     
  //Instancias de puertas y sus conexiones
  not inv1 (s_n, s);
  and and1 (sa, a, s_n);
  and and2 (sb, b, s);
  or or1 (out, sa, sb);
endmodule

module ffdc #(parameter retardo = 0)(input wire clk, reset, carga, d, output reg q);
  //reset asíncrono, carga síncrona
  always @(posedge clk, posedge reset)
    if (reset)
      q <= #retardo 1'b0; //asignación no bloqueante q=0
    else
      if (carga)
        q <= #retardo d; //asignación no bloqueante q=d
endmodule

// Sumador/Restador de 4 bits
module sum_resta4(output wire[3:0] S, output wire c_out, input wire[3:0] A, input wire[3:0] B, input wire resta);
  assign {c_out, S} = (resta == 1) ? A - B + 0 : A + B + 0;
endmodule

booth/cd.v
// M = multiplicando (registro M)
module cd(input wire [2:0] M1, input wire [2:0] Q1, output wire [2:0] salida_Q, output wire [3:0] salida_A, input wire carga_M,input wire carga_Q, input wire carga_A, input wire desplaza_A, input wire desplaza_Q, input wire clk, input wire reset, input wire reset_A, input wire carga_q0, input wire suma, output wire q_1);
 wire [3:0] salida_M;
 wire [3:0] salida_Sum;
 assign carga_qminus1 = carga_Q | desplaza_Q; 
 registro4 A(salida_Sum,salida_A[3], carga_A, desplaza_A, clk, reset_A, salida_A);
 registro4 M({M1[2],M1},0,carga_M,0, clk, reset, salida_M);
 registro3 Q(Q1,salida_A[0],carga_Q,desplaza_Q,clk,reset,salida_Q);
 ffdc Q0(clk,reset,carga_qminus1,salida_Q[0], q_1);
 sum_resta4 sum(salida_Sum,,salida_A, salida_M, suma);

endmodule

booth/uc.v
module unidad_control (input wire [2:0] q, input wire qsub1, reset, clk, output wire CargaQ, DesplazaAQ, CargaA, CargaM, Resta, Fin);
// Variables reg que almacenan el estado actual y el siguiente
reg [2:0] estado, estado_siguiente;
// Codificación de estados
parameter S0 = 3'b000;
parameter S1 = 3'b001;
parameter S2 = 3'b010;
parameter S3 = 3'b011;
parameter S4 = 3'b100;
parameter S5 = 3'b101;
parameter S6 = 3'b110;
parameter S7 = 3'b111;
// Cambios en flacos de subida de clk o reset
always @(posedge clk, posedge reset)
if (reset)
estado <= S0;
else
estado <= estado_siguiente;
// Funcion de transicion
always @(*)
case (estado)
S0: estado_siguiente = S1;
S1: estado_siguiente = S2;
S2: estado_siguiente = S3;
S3: estado_siguiente = S4;
S4: estado_siguiente = S5;
S5: estado_siguiente = S6;
S6: estado_siguiente = S7;
S7: estado_siguiente = S7;
default: estado_siguiente = S0;
endcase
// Funcion de salida
// Utilizar un solo Reset en S0 para todos los registros

assign CargaQ = (estado == S0) ? 1:0;
assign CargaM = (estado == S0) ? 1:0;
assign Reset_A = (estado == S0) ? 1:0;
assign DesplazaAQ = ((estado == S2) || (estado == S4) || (estado == S6)) ? 1:0;

assign CargaA = ( ((estado == S1) || (estado == S3) || (estado == S5)) && (((q[0] == 0) && (qsub1 == 1)) || ((q[0] == 1) && (qsub1 == 0)))) ? 1:0;

assign Resta = ((q[0] == 1) && (qsub1 == 0)) ? 1:0;

assign Fin = (estado == S7) ? 1:0;
endmodule

booth/multiplicador.v
module multiplicador(input wire [2:0] Q1, input wire [2:0] M1, input wire clk, input wire reset, output wire [5:0] resultado, output fin);

wire carga_M;
wire carga_Q;
wire carga_A;
wire desplazaAQ;
wire suma;
wire q_1;
wire [2:0] salidaq;
wire [3:0] salidaA;
unidad_control uc1(salidaq,q_1,reset,clk,carga_Q,desplazaAQ,carga_A,carga_M,suma,fin);
cd cd1(M1,Q1,salidaq,salidaA,carga_M,carga_Q,carga_A,desplazaAQ,desplazaAQ,clk,reset,reset,carga_Q,suma,q_1);

assign resultado = {salidaA[2],salidaA[1],salidaA[0],salidaq[2],salidaq[1],salidaq[0]};

endmodule

booth/multiplicador_tb.v
`timescale 1 ns / 10 ps
module multiplicador_tb;
//Recordar que el caso de -4 en tres bits en el multiplicando dará error en Booth si no hacemos que los registros A y M tengan un bit más (hay overflow) (depende de la implementación del sumador/restador)
parameter NUM_BITS = 3;
parameter NUM_TESTS = (2**(2*NUM_BITS));
parameter MAX_RANGE = (2**(NUM_BITS-1))-1;
parameter MIN_RANGE = - (2**(NUM_BITS-1));
integer contador;
reg clk, start;
wire Fin;
reg signed [NUM_BITS-1:0] multiplicador;
reg signed [NUM_BITS-1:0] multiplicando;
wire [(2*NUM_BITS)-1:0] resultado;
reg signed [(2*NUM_BITS)-1:0] resultado_esperado;

// generación de reloj clk
always //siempre activo, no hay condición de activación
begin
  clk = 1'b0;
  #5;
  clk = 1'b1;
  #5;
end

// Módulo a probar
multiplicador mult(multiplicando, multiplicador, clk, start, resultado, Fin);

initial
begin
  $dumpfile("multiplicador_tb.vcd");
  $dumpvars;
  #10000   //Evita ejecución infinita
  $finish;
end

//Preparación caso inicial
initial
begin
  multiplicando = MIN_RANGE;
  multiplicador = MIN_RANGE;
  contador = 1;
end 

initial
begin
  start = 1'b1;
  #1;
  start = 1'b0;
end

always @(posedge Fin)
begin
  resultado_esperado = multiplicador * multiplicando;
  //Comprobación de resultados
  $write("%d x %d = %d", multiplicando, multiplicador, resultado_esperado);
  if (resultado !== resultado_esperado)
    $display("\tERROR    Obtenido=%b", resultado);
  else
    $display("\tCORRECTO Obtenido=%b", resultado);
  
  #20  //tiempo de espera entre una multiplicación y la siguiente
  if (contador == NUM_TESTS)
    $finish;
  else //Siguiente caso
  begin
    contador = contador + 1;
    if (multiplicador == MAX_RANGE)
    begin
      multiplicador = MIN_RANGE;
      multiplicando = multiplicando + 1;
    end
    else
    begin
      multiplicador = multiplicador + 1;
    end
    start = 1'b1;
    #1;
    start = 1'b0;           
  end
end

endmodule

booth/multiplicador_tb.vcd
$date
	Wed Mar  3 22:21:11 2021
$end
$version
	Icarus Verilog
$end
$timescale
	10ps
$end
$scope module multiplicador_tb $end
$var wire 6 ! resultado [5:0] $end
$var wire 1 " Fin $end
$var reg 1 # clk $end
$var reg 3 $ multiplicador [2:0] $end
$var reg 3 % multiplicando [2:0] $end
$var reg 6 & resultado_esperado [5:0] $end
$var reg 1 ' start $end
$var integer 32 ( contador [31:0] $end
$scope module mult $end
$var wire 3 ) M1 [2:0] $end
$var wire 3 * Q1 [2:0] $end
$var wire 1 # clk $end
$var wire 1 ' reset $end
$var wire 1 + suma $end
$var wire 3 , salidaq [2:0] $end
$var wire 4 - salidaA [3:0] $end
$var wire 6 . resultado [5:0] $end
$var wire 1 / q_1 $end
$var wire 1 " fin $end
$var wire 1 0 desplazaAQ $end
$var wire 1 1 carga_Q $end
$var wire 1 2 carga_M $end
$var wire 1 3 carga_A $end
$scope module cd1 $end
$var wire 3 4 M1 [2:0] $end
$var wire 3 5 Q1 [2:0] $end
$var wire 1 6 carga_qminus1 $end
$var wire 1 # clk $end
$var wire 1 ' reset $end
$var wire 1 ' reset_A $end
$var wire 1 + suma $end
$var wire 4 7 salida_Sum [3:0] $end
$var wire 3 8 salida_Q [2:0] $end
$var wire 4 9 salida_M [3:0] $end
$var wire 4 : salida_A [3:0] $end
$var wire 1 / q_1 $end
$var wire 1 0 desplaza_Q $end
$var wire 1 0 desplaza_A $end
$var wire 1 1 carga_q0 $end
$var wire 1 1 carga_Q $end
$var wire 1 2 carga_M $end
$var wire 1 3 carga_A $end
$scope module A $end
$var wire 1 ; bit_en_desp $end
$var wire 1 # clk $end
$var wire 1 < enable $end
$var wire 1 ' reset $end
$var wire 4 = salida [3:0] $end
$var wire 4 > entrada [3:0] $end
$var wire 1 0 Desplaza $end
$var wire 1 3 Carga $end
$scope module ff0 $end
$var wire 1 < carga $end
$var wire 1 # clk $end
$var wire 1 ? inp_c $end
$var wire 1 @ inp_d $end
$var wire 1 ' reset $end
$var wire 1 3 selc_d $end
$var wire 1 A salida $end
$var wire 1 B inp $end
$scope module ff0 $end
$var wire 1 < carga $end
$var wire 1 # clk $end
$var wire 1 ' reset $end
$var wire 1 B d $end
$var reg 1 A q $end
$upscope $end
$scope module mux0 $end
$var wire 1 @ a $end
$var wire 1 ? b $end
$var wire 1 B out $end
$var wire 1 C s_n $end
$var wire 1 D sa $end
$var wire 1 E sb $end
$var wire 1 3 s $end
$upscope $end
$upscope $end
$scope module ff1 $end
$var wire 1 < carga $end
$var wire 1 # clk $end
$var wire 1 F inp_c $end
$var wire 1 G inp_d $end
$var wire 1 ' reset $end
$var wire 1 3 selc_d $end
$var wire 1 H salida $end
$var wire 1 I inp $end
$scope module ff0 $end
$var wire 1 < carga $end
$var wire 1 # clk $end
$var wire 1 ' reset $end
$var wire 1 I d $end
$var reg 1 H q $end
$upscope $end
$scope module mux0 $end
$var wire 1 G a $end
$var wire 1 F b $end
$var wire 1 I out $end
$var wire 1 J s_n $end
$var wire 1 K sa $end
$var wire 1 L sb $end
$var wire 1 3 s $end
$upscope $end
$upscope $end
$scope module ff2 $end
$var wire 1 < carga $end
$var wire 1 # clk $end
$var wire 1 M inp_c $end
$var wire 1 N inp_d $end
$var wire 1 ' reset $end
$var wire 1 3 selc_d $end
$var wire 1 O salida $end
$var wire 1 P inp $end
$scope module ff0 $end
$var wire 1 < carga $end
$var wire 1 # clk $end
$var wire 1 ' reset $end
$var wire 1 P d $end
$var reg 1 O q $end
$upscope $end
$scope module mux0 $end
$var wire 1 N a $end
$var wire 1 M b $end
$var wire 1 P out $end
$var wire 1 Q s_n $end
$var wire 1 R sa $end
$var wire 1 S sb $end
$var wire 1 3 s $end
$upscope $end
$upscope $end
$scope module ff3 $end
$var wire 1 < carga $end
$var wire 1 # clk $end
$var wire 1 T inp_c $end
$var wire 1 ; inp_d $end
$var wire 1 ' reset $end
$var wire 1 3 selc_d $end
$var wire 1 U salida $end
$var wire 1 V inp $end
$scope module ff0 $end
$var wire 1 < carga $end
$var wire 1 # clk $end
$var wire 1 ' reset $end
$var wire 1 V d $end
$var reg 1 U q $end
$upscope $end
$scope module mux0 $end
$var wire 1 ; a $end
$var wire 1 T b $end
$var wire 1 V out $end
$var wire 1 W s_n $end
$var wire 1 X sa $end
$var wire 1 Y sb $end
$var wire 1 3 s $end
$upscope $end
$upscope $end
$upscope $end
$scope module M $end
$var wire 1 Z Desplaza $end
$var wire 1 [ bit_en_desp $end
$var wire 1 # clk $end
$var wire 1 \ enable $end
$var wire 4 ] entrada [3:0] $end
$var wire 1 ' reset $end
$var wire 4 ^ salida [3:0] $end
$var wire 1 2 Carga $end
$scope module ff0 $end
$var wire 1 \ carga $end
$var wire 1 # clk $end
$var wire 1 _ inp_c $end
$var wire 1 ` inp_d $end
$var wire 1 ' reset $end
$var wire 1 2 selc_d $end
$var wire 1 a salida $end
$var wire 1 b inp $end
$scope module ff0 $end
$var wire 1 \ carga $end
$var wire 1 # clk $end
$var wire 1 ' reset $end
$var wire 1 b d $end
$var reg 1 a q $end
$upscope $end
$scope module mux0 $end
$var wire 1 ` a $end
$var wire 1 _ b $end
$var wire 1 b out $end
$var wire 1 c s_n $end
$var wire 1 d sa $end
$var wire 1 e sb $end
$var wire 1 2 s $end
$upscope $end
$upscope $end
$scope module ff1 $end
$var wire 1 \ carga $end
$var wire 1 # clk $end
$var wire 1 f inp_c $end
$var wire 1 g inp_d $end
$var wire 1 ' reset $end
$var wire 1 2 selc_d $end
$var wire 1 h salida $end
$var wire 1 i inp $end
$scope module ff0 $end
$var wire 1 \ carga $end
$var wire 1 # clk $end
$var wire 1 ' reset $end
$var wire 1 i d $end
$var reg 1 h q $end
$upscope $end
$scope module mux0 $end
$var wire 1 g a $end
$var wire 1 f b $end
$var wire 1 i out $end
$var wire 1 j s_n $end
$var wire 1 k sa $end
$var wire 1 l sb $end
$var wire 1 2 s $end
$upscope $end
$upscope $end
$scope module ff2 $end
$var wire 1 \ carga $end
$var wire 1 # clk $end
$var wire 1 m inp_c $end
$var wire 1 n inp_d $end
$var wire 1 ' reset $end
$var wire 1 2 selc_d $end
$var wire 1 o salida $end
$var wire 1 p inp $end
$scope module ff0 $end
$var wire 1 \ carga $end
$var wire 1 # clk $end
$var wire 1 ' reset $end
$var wire 1 p d $end
$var reg 1 o q $end
$upscope $end
$scope module mux0 $end
$var wire 1 n a $end
$var wire 1 m b $end
$var wire 1 p out $end
$var wire 1 q s_n $end
$var wire 1 r sa $end
$var wire 1 s sb $end
$var wire 1 2 s $end
$upscope $end
$upscope $end
$scope module ff3 $end
$var wire 1 \ carga $end
$var wire 1 # clk $end
$var wire 1 t inp_c $end
$var wire 1 [ inp_d $end
$var wire 1 ' reset $end
$var wire 1 2 selc_d $end
$var wire 1 u salida $end
$var wire 1 v inp $end
$scope module ff0 $end
$var wire 1 \ carga $end
$var wire 1 # clk $end
$var wire 1 ' reset $end
$var wire 1 v d $end
$var reg 1 u q $end
$upscope $end
$scope module mux0 $end
$var wire 1 [ a $end
$var wire 1 t b $end
$var wire 1 v out $end
$var wire 1 w s_n $end
$var wire 1 x sa $end
$var wire 1 y sb $end
$var wire 1 2 s $end
$upscope $end
$upscope $end
$upscope $end
$scope module Q $end
$var wire 1 z bit_en_desp $end
$var wire 1 # clk $end
$var wire 1 { enable $end
$var wire 3 | entrada [2:0] $end
$var wire 1 ' reset $end
$var wire 3 } salida [2:0] $end
$var wire 1 0 Desplaza $end
$var wire 1 1 Carga $end
$scope module ff0 $end
$var wire 1 { carga $end
$var wire 1 # clk $end
$var wire 1 ~ inp_c $end
$var wire 1 !" inp_d $end
$var wire 1 ' reset $end
$var wire 1 1 selc_d $end
$var wire 1 "" salida $end
$var wire 1 #" inp $end
$scope module ff0 $end
$var wire 1 { carga $end
$var wire 1 # clk $end
$var wire 1 ' reset $end
$var wire 1 #" d $end
$var reg 1 "" q $end
$upscope $end
$scope module mux0 $end
$var wire 1 !" a $end
$var wire 1 ~ b $end
$var wire 1 #" out $end
$var wire 1 $" s_n $end
$var wire 1 %" sa $end
$var wire 1 &" sb $end
$var wire 1 1 s $end
$upscope $end
$upscope $end
$scope module ff1 $end
$var wire 1 { carga $end
$var wire 1 # clk $end
$var wire 1 '" inp_c $end
$var wire 1 (" inp_d $end
$var wire 1 ' reset $end
$var wire 1 1 selc_d $end
$var wire 1 )" salida $end
$var wire 1 *" inp $end
$scope module ff0 $end
$var wire 1 { carga $end
$var wire 1 # clk $end
$var wire 1 ' reset $end
$var wire 1 *" d $end
$var reg 1 )" q $end
$upscope $end
$scope module mux0 $end
$var wire 1 (" a $end
$var wire 1 '" b $end
$var wire 1 *" out $end
$var wire 1 +" s_n $end
$var wire 1 ," sa $end
$var wire 1 -" sb $end
$var wire 1 1 s $end
$upscope $end
$upscope $end
$scope module ff2 $end
$var wire 1 { carga $end
$var wire 1 # clk $end
$var wire 1 ." inp_c $end
$var wire 1 z inp_d $end
$var wire 1 ' reset $end
$var wire 1 1 selc_d $end
$var wire 1 /" salida $end
$var wire 1 0" inp $end
$scope module ff0 $end
$var wire 1 { carga $end
$var wire 1 # clk $end
$var wire 1 ' reset $end
$var wire 1 0" d $end
$var reg 1 /" q $end
$upscope $end
$scope module mux0 $end
$var wire 1 z a $end
$var wire 1 ." b $end
$var wire 1 0" out $end
$var wire 1 1" s_n $end
$var wire 1 2" sa $end
$var wire 1 3" sb $end
$var wire 1 1 s $end
$upscope $end
$upscope $end
$upscope $end
$scope module Q0 $end
$var wire 1 6 carga $end
$var wire 1 # clk $end
$var wire 1 4" d $end
$var wire 1 ' reset $end
$var reg 1 / q $end
$upscope $end
$scope module sum $end
$var wire 4 5" A [3:0] $end
$var wire 4 6" B [3:0] $end
$var wire 1 + resta $end
$var wire 1 7" c_out $end
$var wire 4 8" S [3:0] $end
$upscope $end
$upscope $end
$scope module uc1 $end
$var wire 1 # clk $end
$var wire 3 9" q [2:0] $end
$var wire 1 / qsub1 $end
$var wire 1 ' reset $end
$var wire 1 + Resta $end
$var wire 1 :" Reset_A $end
$var wire 1 " Fin $end
$var wire 1 0 DesplazaAQ $end
$var wire 1 1 CargaQ $end
$var wire 1 2 CargaM $end
$var wire 1 3 CargaA $end
$var reg 3 ;" estado [2:0] $end
$var reg 3 <" estado_siguiente [2:0] $end
$upscope $end
$upscope $end
$upscope $end
$enddefinitions $end
#0
$dumpvars
b1 <"
b0 ;"
1:"
b0 9"
b0 8"
07"
b0 6"
b0 5"
04"
13"
02"
01"
10"
0/"
1."
0-"
0,"
0+"
0*"
0)"
0("
0'"
0&"
0%"
0$"
0#"
0""
0!"
0~
b0 }
b100 |
1{
0z
1y
0x
0w
1v
0u
1t
1s
0r
0q
1p
0o
0n
1m
0l
0k
0j
0i
0h
0g
0f
0e
0d
0c
0b
0a
0`
0_
b0 ^
b1100 ]
1\
0[
0Z
0Y
0X
1W
0V
0U
0T
0S
0R
1Q
0P
0O
0N
0M
0L
0K
1J
0I
0H
0G
0F
0E
0D
1C
0B
0A
0@
0?
b0 >
b0 =
0<
0;
b0 :
b0 9
b0 8
b0 7
16
b100 5
b100 4
03
12
11
00
0/
b0 .
b0 -
b0 ,
0+
b100 *
b100 )
b1 (
1'
bx &
b100 %
b100 $
0#
0"
b0 !
$end
#100
0'
#500
1*"
1i
00"
1,"
0v
1r
1k
1T
1M
03"
11"
1+"
1$"
0{
06
0y
1w
0s
1q
1j
1c
0\
b1100 7
b1100 >
b1100 8"
01
02
0:"
1("
b100 !
b100 .
1n
1g
b10 <"
b100 ,
b100 8
b100 }
b100 9"
1/"
1u
b1100 9
b1100 ^
b1100 6"
1o
b1 ;"
1#
#1000
0#
#1500
1{
1<
16
10
b11 <"
b10 ;"
1#
#2000
0#
#2500
0{
0<
06
00
0*"
1#"
0,"
1%"
0("
1!"
b10 !
b10 .
b100 <"
0/"
b10 ,
b10 8
b10 }
b10 9"
1)"
b11 ;"
1#
#3000
0#
#3500
1{
1<
16
10
b101 <"
b100 ;"
1#
#4000
0#
#4500
1P
0W
1S
0Q
0J
0C
0T
13
b100 7
b100 >
b100 8"
17"
0{
1<
06
1+
00
0#"
0%"
0!"
14"
b1 !
b1 .
b110 <"
0)"
b1 ,
b1 8
b1 }
b1 9"
1""
b101 ;"
1#
#5000
0#
#5500
1I
1K
1W
1Q
1J
1C
0V
0P
1{
16
03
0Y
0S
10
1T
0M
b1000 7
b1000 >
b1000 8"
b111 <"
1G
b100001 !
b100001 .
b110 ;"
b100 -
b100 :
b100 =
b100 5"
1O
1#
#6000
0#
#6500
07"
0{
0<
06
0+
0I
1T
1M
1F
1B
00
b10000 &
0K
b1110 7
b1110 >
b1110 8"
1D
1"
04"
0G
1@
b10000 !
b10000 .
1/
b0 ,
b0 8
b0 }
b0 9"
0""
0O
b10 -
b10 :
b10 =
b10 5"
1H
b111 ;"
1#
#7000
0#
#7500
1#
#8000
0#
#8500
10"
1v
1b
0i
0T
0M
0F
0B
13"
01"
0+"
0$"
1{
16
1y
0w
1s
0q
0j
1e
0c
1\
0r
0k
b0 7
b0 >
b0 8"
0D
11
12
1:"
0"
0n
0g
0@
b0 !
b0 .
b1 <"
0/
0u
b0 9
b0 ^
b0 6"
0o
b0 -
b0 :
b0 =
b0 5"
0H
b0 ;"
1_
1#
1'
b1101 ]
b101 $
b101 )
b101 4
b10 (
#8600
0'
#9000
0#
#9500
1*"
1i
00"
1,"
0v
1r
1k
0b
03"
11"
1+"
1$"
0{
06
0y
1w
0s
1q
1j
0e
1c
0\
1T
1M
1?
01
02
0:"
b1101 7
b1101 >
b1101 8"
b10 <"
1g
1n
1("
b100 !
b100 .
b1 ;"
1a
1o
b1101 9
b1101 ^
b1101 6"
1u
b100 ,
b100 8
b100 }
b100 9"
1/"
1#
#10000
0#
#10500
1{
1<
16
10
b11 <"
b10 ;"
1#
#11000
0#
#11500
0{
0<
06
00
1#"
0*"
1%"
0,"
b100 <"
1!"
0("
b10 !
b10 .
b11 ;"
1)"
b10 ,
b10 8
b10 }
b10 9"
0/"
1#
#12000
0#
#12500
1{
1<
16
10
b101 <"
b100 ;"
1#
#13000
0#
#13500
1I
1B
0W
0Q
1L
0J
1E
0C
0T
0M
1F
13
b11 7
b11 >
b11 8"
17"
0{
1<
06
00
1+
0#"
0%"
b110 <"
14"
0!"
b1 !
b1 .
b101 ;"
1""
b1 ,
b1 8
b1 }
b1 9"
0)"
1#
#14000
0#
#14500
0I
1D
1B
1W
1Q
0L
1J
1C
0E
1{
16
03
1M
0?
10"
10
b110 7
b110 >
b110 8"
12"
1@
1z
b11001 !
b11001 .
b111 <"
1H
b11 -
b11 :
b11 =
b11 5"
1A
b110 ;"
1#
#15000
0#
#15500
1T
07"
0{
0<
06
00
b1100 &
1F
0B
1*"
0+
1"
b1110 7
b1110 >
b1110 8"
0D
1,"
0@
04"
1("
b1100 !
b1100 .
b111 ;"
b1 -
b1 :
b1 =
b1 5"
0H
0""
b100 ,
b100 8
b100 }
b100 9"
1/"
1/
1#
#16000
0#
#16500
1#
#17000
0#
#17500
1v
13"
01"
0+"
0$"
1{
16
1y
0w
1s
0q
1l
0j
0c
1\
10"
1i
0T
0M
0F
1p
0*"
11
12
1:"
0"
02"
0k
b0 7
b0 >
b0 8"
0r
0,"
b1 <"
0z
0g
0n
0("
b0 !
b0 .
b0 ;"
b0 -
b0 :
b0 =
b0 5"
0A
0a
0o
b0 9
b0 ^
b0 6"
0u
b0 ,
b0 8
b0 }
b0 9"
0/"
0/
0_
1f
1#
1'
b1110 ]
b110 $
b110 )
b110 4
b11 (
#17600
0'
#18000
0#
#18500
1*"
1b
00"
1,"
0v
1r
1k
1d
1T
1M
1F
03"
11"
1+"
1$"
0{
06
0y
1w
0s
1q
0l
1j
1c
0\
b1110 7
b1110 >
b1110 8"
01
02
0:"
1("
b100 !
b100 .
1n
1g
1`
b10 <"
b100 ,
b100 8
b100 }
b100 9"
1/"
1u
1o
b1110 9
b1110 ^
b1110 6"
1h
b1 ;"
1#
#19000
0#
#19500
1{
1<
16
10
b11 <"
b10 ;"
1#
#20000
0#
#20500
0{
0<
06
00
0*"
1#"
0,"
1%"
0("
1!"
b10 !
b10 .
b100 <"
0/"
b10 ,
b10 8
b10 }
b10 9"
1)"
b11 ;"
1#
#21000
0#
#21500
1{
1<
16
10
b101 <"
b100 ;"
1#
#22000
0#
#22500
1I
0W
0Q
1L
0J
0C
0T
0M
13
b10 7
b10 >
b10 8"
17"
0{
1<
06
1+
00
0#"
0%"
0!"
14"
b1 !
b1 .
b110 <"
0)"
b1 ,
b1 8
b1 }
b1 9"
1""
b101 ;"
1#
#23000
0#
#23500
1B
1D
1W
1Q
1J
1C
0P
0I
1{
16
03
0S
0L
10
1M
0F
b100 7
b100 >
b100 8"
b111 <"
1@
b10001 !
b10001 .
b110 ;"
b10 -
b10 :
b10 =
b10 5"
1H
1#
#24000
0#
#24500
1T
07"
0{
0<
06
0+
0B
1M
1F
1?
10"
00
b1000 &
0D
b1111 7
b1111 >
b1111 8"
12"
1"
04"
0@
1z
b1000 !
b1000 .
1/
b0 ,
b0 8
b0 }
b0 9"
0""
0H
b1 -
b1 :
b1 =
b1 5"
1A
b111 ;"
1#
#25000
0#
#25500
1#
#26000
0#
#26500
1v
0T
0M
0F
0?
13"
01"
0+"
0$"
1{
16
1y
0w
1s
0q
1l
0j
1e
0c
1\
0r
0k
0d
b0 7
b0 >
b0 8"
02"
11
12
1:"
0"
0n
0g
0`
0z
b0 !
b0 .
b1 <"
0/
0u
0o
b0 9
b0 ^
b0 6"
0h
b0 -
b0 :
b0 =
b0 5"
0A
b0 ;"
1_
1#
1'
b1111 ]
b111 $
b111 )
b111 4
b100 (
#26600
0'
#27000
0#
#27500
1*"
00"
1,"
0v
1r
1k
1d
03"
11"
1+"
1$"
0{
06
0y
1w
0s
1q
0l
1j
0e
1c
0\
1T
1M
1F
1?
01
02
0:"
b1111 7
b1111 >
b1111 8"
b10 <"
1`
1g
1n
1("
b100 !
b100 .
b1 ;"
1a
1h
1o
b1111 9
b1111 ^
b1111 6"
1u
b100 ,
b100 8
b100 }
b100 9"
1/"
1#
#28000
0#
#28500
1{
1<
16
10
b11 <"
b10 ;"
1#
#29000
0#
#29500
0{
0<
06
00
1#"
0*"
1%"
0,"
b100 <"
1!"
0("
b10 !
b10 .
b11 ;"
1)"
b10 ,
b10 8
b10 }
b10 9"
0/"
1#
#30000
0#
#30500
1{
1<
16
10
b101 <"
b100 ;"
1#
#31000
0#
#31500
1B
0W
0Q
0J
1E
0C
0T
0M
0F
13
b1 7
b1 >
b1 8"
17"
0{
1<
06
00
1+
0#"
0%"
b110 <"
14"
0!"
b1 !
b1 .
b101 ;"
1""
b1 ,
b1 8
b1 }
b1 9"
0)"
1#
#32000
0#
#32500
0B
1W
1Q
1J
1C
0E
1{
16
03
1F
0?
10"
10
b10 7
b10 >
b10 8"
12"
1z
b1001 !
b1001 .
b111 <"
b1 -
b1 :
b1 =
b1 5"
1A
b110 ;"
1#
#33000
0#
#33500
1T
1M
07"
0{
0<
06
00
b100 &
1F
1?
00"
1*"
0+
1"
b1111 7
b1111 >
b1111 8"
02"
1,"
0z
04"
1("
b100 !
b100 .
b111 ;"
b0 -
b0 :
b0 =
b0 5"
0A
0""
b100 ,
b100 8
b100 }
b100 9"
1/"
1/
1#
#34000
0#
#34500
1#
#35000
0#
#35500
10"
13"
01"
0+"
0$"
1{
16
0w
0q
0j
0c
1\
0b
0i
0T
0M
0F
0?
0p
0*"
11
12
1:"
0"
0d
0k
b0 7
b0 >
b0 8"
0r
0,"
b1 <"
0`
0g
0n
0("
b0 !
b0 .
b0 ;"
0a
0h
0o
b0 9
b0 ^
b0 6"
0u
b0 ,
b0 8
b0 }
b0 9"
0/"
0/
0t
0_
0f
0m
1#
1'
b0 ]
b0 $
b0 )
b0 4
b101 (
#35600
0'
#36000
0#
#36500
1*"
00"
1,"
03"
11"
1+"
1$"
0{
06
1w
1q
1j
1c
0\
01
02
0:"
1("
b100 !
b100 .
b10 <"
b100 ,
b100 8
b100 }
b100 9"
1/"
b1 ;"
1#
#37000
0#
#37500
1{
1<
16
10
b11 <"
b10 ;"
1#
#38000
0#
#38500
0{
0<
06
00
0*"
1#"
0,"
1%"
0("
1!"
b10 !
b10 .
b100 <"
0/"
b10 ,
b10 8
b10 }
b10 9"
1)"
b11 ;"
1#
#39000
0#
#39500
1{
1<
16
10
b101 <"
b100 ;"
1#
#40000
0#
#40500
0W
0Q
0J
0C
13
0{
1<
06
1+
00
0#"
0%"
0!"
14"
b1 !
b1 .
b110 <"
0)"
b1 ,
b1 8
b1 }
b1 9"
1""
b101 ;"
1#
#41000
0#
#41500
1W
1Q
1J
1C
1{
16
03
10
b111 <"
b110 ;"
1#
#42000
0#
#42500
0{
0<
06
0+
00
b0 &
1"
04"
b0 !
b0 .
1/
b0 ,
b0 8
b0 }
b0 9"
0""
b111 ;"
1#
#43000
0#
#43500
1#
#44000
0#
#44500
10"
1b
13"
01"
0+"
0$"
1{
16
0w
0q
0j
1e
0c
1\
11
12
1:"
0"
b1 <"
0/
b0 ;"
1_
1#
1'
b1 ]
b1 $
b1 )
b1 4
b110 (
#44600
0'
#45000
0#
#45500
1*"
00"
1,"
0b
03"
11"
1+"
1$"
0{
06
1w
1q
1j
0e
1c
0\
1?
01
02
0:"
b1 7
b1 >
b1 8"
b10 <"
1("
b100 !
b100 .
b1 ;"
b1 9
b1 ^
b1 6"
1a
b100 ,
b100 8
b100 }
b100 9"
1/"
1#
#46000
0#
#46500
1{
1<
16
10
b11 <"
b10 ;"
1#
#47000
0#
#47500
0{
0<
06
00
1#"
0*"
1%"
0,"
b100 <"
1!"
0("
b10 !
b10 .
b11 ;"
1)"
b10 ,
b10 8
b10 }
b10 9"
0/"
1#
#48000
0#
#48500
1{
1<
16
10
b101 <"
b100 ;"
1#
#49000
0#
