componentes.v
`timescale 1 ns / 10 ps


// Registro de 4 bits, soporta Carga de entrada, reseteo y desplazamiento aritmético o lógico
// La línea de Carga indica que se va a asignar un nuevo valor al registro que viene por "entrada"
// La línea de Desplaza indica que se va a desplazar el contenido del registro. El bit más significativo se completa con la entrada "bit_en_desp"
module registro4 (input wire [3:0] entrada, input wire bit_en_desp, input wire Carga, Desplaza, clk, reset, output wire [3:0] salida);
  wire enable;

  assign enable = Carga | Desplaza; //Si se carga o desplaza se habilitan en modificación los biestables

  cdaff ff0(Carga, entrada[0], salida[1], clk, reset, enable, salida[0]);
  cdaff ff1(Carga, entrada[1], salida[2], clk, reset, enable, salida[1]);
  cdaff ff2(Carga, entrada[2], salida[3], clk, reset, enable, salida[2]);
  cdaff ff3(Carga, entrada[3], bit_en_desp, clk, reset, enable, salida[3]); //entra un bit en el desplaz
endmodule

// Registro de 3 bits, soporta Carga de entrada, reseteo y desplazamiento aritmético o lógico
// La línea de Carga indica que se va a asignar un nuevo valor al registro que viene por "entrada"
// La línea de Desplaza indica que se va a desplazar el contenido del registro. El bit más significativo se completa con la entrada "bit_en_desp"
module registro3 (input wire [2:0] entrada, input wire bit_en_desp, input wire Carga, Desplaza, clk, reset, output wire [2:0] salida);
  wire enable;
  
  assign enable = Carga | Desplaza; //Si se carga o desplaza se habilitan en modificación los biestables

  cdaff ff0(Carga, entrada[0], salida[1], clk, reset, enable, salida[0]);
  cdaff ff1(Carga, entrada[1], salida[2], clk, reset, enable, salida[1]);
  cdaff ff2(Carga, entrada[2], bit_en_desp, clk, reset, enable, salida[2]); //entra un bit en el desplaz
endmodule

//Biestable con entrada de mux para aceptar dos entradas posibles
module cdaff (input wire selc_d, inp_c, inp_d, clk, reset, carga, output wire salida);
  wire inp;
  
  ffdc ff0(clk, reset, carga, inp, salida);
  mux2_1_i1 mux0(inp, inp_d, inp_c, selc_d);
endmodule

//Mux de dos entradas de 1 bit realizado a partir de puertas 
module mux2_1_i1(output wire out, input wire a, b, s);
  //Declaración de conexiones internas
  wire  s_n, sa, sb;     
  //Instancias de puertas y sus conexiones
  not inv1 (s_n, s);
  and and1 (sa, a, s_n);
  and and2 (sb, b, s);
  or or1 (out, sa, sb);
endmodule

module ffdc #(parameter retardo = 0)(input wire clk, reset, carga, d, output reg q);
  //reset asíncrono, carga síncrona
  always @(posedge clk, posedge reset)
    if (reset)
      q <= #retardo 1'b0; //asignación no bloqueante q=0
    else
      if (carga)
        q <= #retardo d; //asignación no bloqueante q=d
endmodule

// Sumador/Restador de 4 bits
module sum_resta4(output wire[3:0] S, output wire c_out, input wire[3:0] A, input wire[3:0] B, input wire resta);
  assign {c_out, S} = (resta == 1) ? A - B + 0 : A + B + 0;
endmodule

booth/cd.v
// M = multiplicando (registro M)
module cd(input wire [2:0] M1, input wire [2:0] Q1, output wire [2:0] salida_Q, output wire [3:0] salida_A, input wire carga_M,input wire carga_Q, input wire carga_A, input wire desplaza_A, input wire desplaza_Q, input wire clk, input wire reset, input wire reset_A, input wire carga_q0, input wire suma, output wire q_1);
 wire [3:0] salida_M;
 wire [3:0] salida_Sum;
 assign carga_qminus1 = carga_Q | desplaza_Q; 
 registro4 A(salida_Sum,salida_A[3], carga_A, desplaza_A, clk, reset_A, salida_A);
 registro4 M({M1[2],M1},0,carga_M,0, clk, reset, salida_M);
 registro3 Q(Q1,salida_A[0],carga_Q,desplaza_Q,clk,reset,salida_Q);
 ffdc Q0(clk,reset,carga_qminus1,salida_Q[0], q_1);
 sum_resta4 sum(salida_Sum,,salida_A, salida_M, suma);

endmodule

booth/uc.v
module unidad_control (input wire [2:0] q, input wire qsub1, reset, clk, output wire CargaQ, DesplazaAQ, CargaA, CargaM, Resta, Fin);
// Variables reg que almacenan el estado actual y el siguiente
reg [2:0] estado, estado_siguiente;
// Codificación de estados
parameter S0 = 3'b000;
parameter S1 = 3'b001;
parameter S2 = 3'b010;
parameter S3 = 3'b011;
parameter S4 = 3'b100;
parameter S5 = 3'b101;
parameter S6 = 3'b110;
parameter S7 = 3'b111;
// Cambios en flacos de subida de clk o reset
always @(posedge clk, posedge reset)
if (reset)
estado <= S0;
else
estado <= estado_siguiente;
// Funcion de transicion
always @(*)
case (estado)
S0: estado_siguiente = S1;
S1: estado_siguiente = S2;
S2: estado_siguiente = S3;
S3: estado_siguiente = S4;
S4: estado_siguiente = S5;
S5: estado_siguiente = S6;
S6: estado_siguiente = S7;
S7: estado_siguiente = S7;
default: estado_siguiente = S0;
endcase
// Funcion de salida
// Utilizar un solo Reset en S0 para todos los registros

assign CargaQ = (estado == S0) ? 1:0;
assign CargaM = (estado == S0) ? 1:0;
assign Reset_A = (estado == S0) ? 1:0;
assign DesplazaAQ = ((estado == S2) || (estado == S4) || (estado == S6)) ? 1:0;

assign CargaA = ( ((estado == S1) || (estado == S3) || (estado == S5)) && (((q[0] == 0) && (qsub1 == 1)) || ((q[0] == 1) && (qsub1 == 0)))) ? 1:0;

assign Resta = ((q[0] == 1) && (qsub1 == 0)) ? 1:0;

assign Fin = (estado == S7) ? 1:0;
endmodule

booth/multiplicador.v
module multiplicador(input wire [2:0] Q1, input wire [2:0] M1, input wire clk, input wire reset, output wire [5:0] resultado, output fin);

wire carga_M;
wire carga_Q;
wire carga_A;
wire desplazaAQ;
wire suma;
wire q_1;
wire [2:0] salidaq;
wire [3:0] salidaA;
unidad_control uc1(salidaq,q_1,reset,clk,carga_Q,desplazaAQ,carga_A,carga_M,suma,fin);
wire reset_a;
//uc_2 uc1(salidaq[0],q_1,reset,clk,carga_Q,desplazaAQ,carga_A,carga_M,suma,fin,reset_a);
cd cd1(M1,Q1,salidaq,salidaA,carga_M,carga_Q,carga_A,desplazaAQ,desplazaAQ,clk,reset,reset,carga_Q,suma,q_1);
//cd cd1(M1,Q1,salidaq,salidaA,carga_M,carga_Q,carga_A,desplazaAQ,desplazaAQ,clk,reset,reset_a,carga_Q,suma,q_1);

assign resultado = {salidaA[2],salidaA[1],salidaA[0],salidaq[2],salidaq[1],salidaq[0]};

endmodule

booth/multiplicador_tb.v
`timescale 1 ns / 10 ps
module multiplicador_tb;
//Recordar que el caso de -4 en tres bits en el multiplicando dará error en Booth si no hacemos que los registros A y M tengan un bit más (hay overflow) (depende de la implementación del sumador/restador)
parameter NUM_BITS = 3;
parameter NUM_TESTS = (2**(2*NUM_BITS));
parameter MAX_RANGE = (2**(NUM_BITS-1))-1;
parameter MIN_RANGE = - (2**(NUM_BITS-1));
integer contador;
reg clk, start;
wire Fin;
reg signed [NUM_BITS-1:0] multiplicador;
reg signed [NUM_BITS-1:0] multiplicando;
wire [(2*NUM_BITS)-1:0] resultado;
reg signed [(2*NUM_BITS)-1:0] resultado_esperado;

// generación de reloj clk
always //siempre activo, no hay condición de activación
begin
  clk = 1'b0;
  #5;
  clk = 1'b1;
  #5;
end

// Módulo a probar
multiplicador mult(multiplicando, multiplicador, clk, start, resultado, Fin);

initial
begin
  $dumpfile("multiplicador_tb.vcd");
  $dumpvars;
  #10000   //Evita ejecución infinita
  $finish;
end

//Preparación caso inicial
initial
begin
  multiplicando = MIN_RANGE;
  multiplicador = MIN_RANGE;
  contador = 1;
end 

initial
begin
  start = 1'b1;
  #1;
  start = 1'b0;
end

always @(posedge Fin)
begin
  resultado_esperado = multiplicador * multiplicando;
  //Comprobación de resultados
  $write("%d x %d = %d", multiplicando, multiplicador, resultado_esperado);
  if (resultado !== resultado_esperado)
    $display("\tERROR    Obtenido=%b", resultado);
  else
    $display("\tCORRECTO Obtenido=%b", resultado);
  
  #20  //tiempo de espera entre una multiplicación y la siguiente
  if (contador == NUM_TESTS)
    $finish;
  else //Siguiente caso
  begin
    contador = contador + 1;
    if (multiplicador == MAX_RANGE)
    begin
      multiplicador = MIN_RANGE;
      multiplicando = multiplicando + 1;
    end
    else
    begin
      multiplicador = multiplicador + 1;
    end
    start = 1'b1;
    #1;
    start = 1'b0;           
  end
end

endmodule

booth/counter.v
module contador(input wire clk, reset, output wire q0, q1, q2);
// clk , reset , enable , d , q 

wire q0_neg, q1_neg, q2_neg;
assign q0_neg = -q0;
assign q1_neg = -q1;
assign q2_neg = -q2;

ffdc ff0 (clk, reset, ,q0_neg ,q0);
ffdc ff1 (q0_neg, reset, ,q1_neg,q1);
ffdc ff2 (q1_neg, reset, ,q2_neg, q2);
endmodule

booth/multiplicador_tb.vcd
$date
	Mon Mar 15 19:12:09 2021
$end
$version
	Icarus Verilog
$end
$timescale
	10ps
$end
$scope module contador $end
$var wire 1 ! clk $end
$var wire 1 " reset $end
$var wire 1 # q2_neg $end
$var wire 1 $ q2 $end
$var wire 1 % q1_neg $end
$var wire 1 & q1 $end
$var wire 1 ' q0_neg $end
$var wire 1 ( q0 $end
$scope module ff0 $end
$var wire 1 ) carga $end
$var wire 1 ! clk $end
$var wire 1 ' d $end
$var wire 1 " reset $end
$var reg 1 ( q $end
$upscope $end
$scope module ff1 $end
$var wire 1 * carga $end
$var wire 1 ' clk $end
$var wire 1 % d $end
$var wire 1 " reset $end
$var reg 1 & q $end
$upscope $end
$scope module ff2 $end
$var wire 1 + carga $end
$var wire 1 % clk $end
$var wire 1 # d $end
$var wire 1 " reset $end
$var reg 1 $ q $end
$upscope $end
$upscope $end
$scope module multiplicador_tb $end
$var wire 6 , resultado [5:0] $end
$var wire 1 - Fin $end
$var reg 1 . clk $end
$var reg 3 / multiplicador [2:0] $end
$var reg 3 0 multiplicando [2:0] $end
$var reg 6 1 resultado_esperado [5:0] $end
$var reg 1 2 start $end
$var integer 32 3 contador [31:0] $end
$scope module mult $end
$var wire 3 4 M1 [2:0] $end
$var wire 3 5 Q1 [2:0] $end
$var wire 1 . clk $end
$var wire 1 2 reset $end
$var wire 1 6 suma $end
$var wire 3 7 salidaq [2:0] $end
$var wire 4 8 salidaA [3:0] $end
$var wire 6 9 resultado [5:0] $end
$var wire 1 : q_1 $end
$var wire 1 - fin $end
$var wire 1 ; desplazaAQ $end
$var wire 1 < carga_Q $end
$var wire 1 = carga_M $end
$var wire 1 > carga_A $end
$scope module cd1 $end
$var wire 3 ? M1 [2:0] $end
$var wire 3 @ Q1 [2:0] $end
$var wire 1 A carga_qminus1 $end
$var wire 1 . clk $end
$var wire 1 2 reset $end
$var wire 1 2 reset_A $end
$var wire 1 6 suma $end
$var wire 4 B salida_Sum [3:0] $end
$var wire 3 C salida_Q [2:0] $end
$var wire 4 D salida_M [3:0] $end
$var wire 4 E salida_A [3:0] $end
$var wire 1 : q_1 $end
$var wire 1 ; desplaza_Q $end
$var wire 1 ; desplaza_A $end
$var wire 1 < carga_q0 $end
$var wire 1 < carga_Q $end
$var wire 1 = carga_M $end
$var wire 1 > carga_A $end
$scope module A $end
$var wire 1 F bit_en_desp $end
$var wire 1 . clk $end
$var wire 1 G enable $end
$var wire 1 2 reset $end
$var wire 4 H salida [3:0] $end
$var wire 4 I entrada [3:0] $end
$var wire 1 ; Desplaza $end
$var wire 1 > Carga $end
$scope module ff0 $end
$var wire 1 G carga $end
$var wire 1 . clk $end
$var wire 1 J inp_c $end
$var wire 1 K inp_d $end
$var wire 1 2 reset $end
$var wire 1 > selc_d $end
$var wire 1 L salida $end
$var wire 1 M inp $end
$scope module ff0 $end
$var wire 1 G carga $end
$var wire 1 . clk $end
$var wire 1 2 reset $end
$var wire 1 M d $end
$var reg 1 L q $end
$upscope $end
$scope module mux0 $end
$var wire 1 K a $end
$var wire 1 J b $end
$var wire 1 M out $end
$var wire 1 N s_n $end
$var wire 1 O sa $end
$var wire 1 P sb $end
$var wire 1 > s $end
$upscope $end
$upscope $end
$scope module ff1 $end
$var wire 1 G carga $end
$var wire 1 . clk $end
$var wire 1 Q inp_c $end
$var wire 1 R inp_d $end
$var wire 1 2 reset $end
$var wire 1 > selc_d $end
$var wire 1 S salida $end
$var wire 1 T inp $end
$scope module ff0 $end
$var wire 1 G carga $end
$var wire 1 . clk $end
$var wire 1 2 reset $end
$var wire 1 T d $end
$var reg 1 S q $end
$upscope $end
$scope module mux0 $end
$var wire 1 R a $end
$var wire 1 Q b $end
$var wire 1 T out $end
$var wire 1 U s_n $end
$var wire 1 V sa $end
$var wire 1 W sb $end
$var wire 1 > s $end
$upscope $end
$upscope $end
$scope module ff2 $end
$var wire 1 G carga $end
$var wire 1 . clk $end
$var wire 1 X inp_c $end
$var wire 1 Y inp_d $end
$var wire 1 2 reset $end
$var wire 1 > selc_d $end
$var wire 1 Z salida $end
$var wire 1 [ inp $end
$scope module ff0 $end
$var wire 1 G carga $end
$var wire 1 . clk $end
$var wire 1 2 reset $end
$var wire 1 [ d $end
$var reg 1 Z q $end
$upscope $end
$scope module mux0 $end
$var wire 1 Y a $end
$var wire 1 X b $end
$var wire 1 [ out $end
$var wire 1 \ s_n $end
$var wire 1 ] sa $end
$var wire 1 ^ sb $end
$var wire 1 > s $end
$upscope $end
$upscope $end
$scope module ff3 $end
$var wire 1 G carga $end
$var wire 1 . clk $end
$var wire 1 _ inp_c $end
$var wire 1 F inp_d $end
$var wire 1 2 reset $end
$var wire 1 > selc_d $end
$var wire 1 ` salida $end
$var wire 1 a inp $end
$scope module ff0 $end
$var wire 1 G carga $end
$var wire 1 . clk $end
$var wire 1 2 reset $end
$var wire 1 a d $end
$var reg 1 ` q $end
$upscope $end
$scope module mux0 $end
$var wire 1 F a $end
$var wire 1 _ b $end
$var wire 1 a out $end
$var wire 1 b s_n $end
$var wire 1 c sa $end
$var wire 1 d sb $end
$var wire 1 > s $end
$upscope $end
$upscope $end
$upscope $end
$scope module M $end
$var wire 1 e Desplaza $end
$var wire 1 f bit_en_desp $end
$var wire 1 . clk $end
$var wire 1 g enable $end
$var wire 4 h entrada [3:0] $end
$var wire 1 2 reset $end
$var wire 4 i salida [3:0] $end
$var wire 1 = Carga $end
$scope module ff0 $end
$var wire 1 g carga $end
$var wire 1 . clk $end
$var wire 1 j inp_c $end
$var wire 1 k inp_d $end
$var wire 1 2 reset $end
$var wire 1 = selc_d $end
$var wire 1 l salida $end
$var wire 1 m inp $end
$scope module ff0 $end
$var wire 1 g carga $end
$var wire 1 . clk $end
$var wire 1 2 reset $end
$var wire 1 m d $end
$var reg 1 l q $end
$upscope $end
$scope module mux0 $end
$var wire 1 k a $end
$var wire 1 j b $end
$var wire 1 m out $end
$var wire 1 n s_n $end
$var wire 1 o sa $end
$var wire 1 p sb $end
$var wire 1 = s $end
$upscope $end
$upscope $end
$scope module ff1 $end
$var wire 1 g carga $end
$var wire 1 . clk $end
$var wire 1 q inp_c $end
$var wire 1 r inp_d $end
$var wire 1 2 reset $end
$var wire 1 = selc_d $end
$var wire 1 s salida $end
$var wire 1 t inp $end
$scope module ff0 $end
$var wire 1 g carga $end
$var wire 1 . clk $end
$var wire 1 2 reset $end
$var wire 1 t d $end
$var reg 1 s q $end
$upscope $end
$scope module mux0 $end
$var wire 1 r a $end
$var wire 1 q b $end
$var wire 1 t out $end
$var wire 1 u s_n $end
$var wire 1 v sa $end
$var wire 1 w sb $end
$var wire 1 = s $end
$upscope $end
$upscope $end
$scope module ff2 $end
$var wire 1 g carga $end
$var wire 1 . clk $end
$var wire 1 x inp_c $end
$var wire 1 y inp_d $end
$var wire 1 2 reset $end
$var wire 1 = selc_d $end
$var wire 1 z salida $end
$var wire 1 { inp $end
$scope module ff0 $end
$var wire 1 g carga $end
$var wire 1 . clk $end
$var wire 1 2 reset $end
$var wire 1 { d $end
$var reg 1 z q $end
$upscope $end
$scope module mux0 $end
$var wire 1 y a $end
$var wire 1 x b $end
$var wire 1 { out $end
$var wire 1 | s_n $end
$var wire 1 } sa $end
$var wire 1 ~ sb $end
$var wire 1 = s $end
$upscope $end
$upscope $end
$scope module ff3 $end
$var wire 1 g carga $end
$var wire 1 . clk $end
$var wire 1 !" inp_c $end
$var wire 1 f inp_d $end
$var wire 1 2 reset $end
$var wire 1 = selc_d $end
$var wire 1 "" salida $end
$var wire 1 #" inp $end
$scope module ff0 $end
$var wire 1 g carga $end
$var wire 1 . clk $end
$var wire 1 2 reset $end
$var wire 1 #" d $end
$var reg 1 "" q $end
$upscope $end
$scope module mux0 $end
$var wire 1 f a $end
$var wire 1 !" b $end
$var wire 1 #" out $end
$var wire 1 $" s_n $end
$var wire 1 %" sa $end
$var wire 1 &" sb $end
$var wire 1 = s $end
$upscope $end
$upscope $end
$upscope $end
$scope module Q $end
$var wire 1 '" bit_en_desp $end
$var wire 1 . clk $end
$var wire 1 (" enable $end
$var wire 3 )" entrada [2:0] $end
$var wire 1 2 reset $end
$var wire 3 *" salida [2:0] $end
$var wire 1 ; Desplaza $end
$var wire 1 < Carga $end
$scope module ff0 $end
$var wire 1 (" carga $end
$var wire 1 . clk $end
$var wire 1 +" inp_c $end
$var wire 1 ," inp_d $end
$var wire 1 2 reset $end
$var wire 1 < selc_d $end
$var wire 1 -" salida $end
$var wire 1 ." inp $end
$scope module ff0 $end
$var wire 1 (" carga $end
$var wire 1 . clk $end
$var wire 1 2 reset $end
$var wire 1 ." d $end
$var reg 1 -" q $end
$upscope $end
$scope module mux0 $end
$var wire 1 ," a $end
$var wire 1 +" b $end
$var wire 1 ." out $end
$var wire 1 /" s_n $end
$var wire 1 0" sa $end
$var wire 1 1" sb $end
$var wire 1 < s $end
$upscope $end
$upscope $end
$scope module ff1 $end
$var wire 1 (" carga $end
$var wire 1 . clk $end
$var wire 1 2" inp_c $end
$var wire 1 3" inp_d $end
$var wire 1 2 reset $end
$var wire 1 < selc_d $end
$var wire 1 4" salida $end
$var wire 1 5" inp $end
$scope module ff0 $end
$var wire 1 (" carga $end
$var wire 1 . clk $end
$var wire 1 2 reset $end
$var wire 1 5" d $end
$var reg 1 4" q $end
$upscope $end
$scope module mux0 $end
$var wire 1 3" a $end
$var wire 1 2" b $end
$var wire 1 5" out $end
$var wire 1 6" s_n $end
$var wire 1 7" sa $end
$var wire 1 8" sb $end
$var wire 1 < s $end
$upscope $end
$upscope $end
$scope module ff2 $end
$var wire 1 (" carga $end
$var wire 1 . clk $end
$var wire 1 9" inp_c $end
$var wire 1 '" inp_d $end
$var wire 1 2 reset $end
$var wire 1 < selc_d $end
$var wire 1 :" salida $end
$var wire 1 ;" inp $end
$scope module ff0 $end
$var wire 1 (" carga $end
$var wire 1 . clk $end
$var wire 1 2 reset $end
$var wire 1 ;" d $end
$var reg 1 :" q $end
$upscope $end
$scope module mux0 $end
$var wire 1 '" a $end
$var wire 1 9" b $end
$var wire 1 ;" out $end
$var wire 1 <" s_n $end
$var wire 1 =" sa $end
$var wire 1 >" sb $end
$var wire 1 < s $end
$upscope $end
$upscope $end
$upscope $end
$scope module Q0 $end
$var wire 1 A carga $end
$var wire 1 . clk $end
$var wire 1 ?" d $end
$var wire 1 2 reset $end
$var reg 1 : q $end
$upscope $end
$scope module sum $end
$var wire 4 @" A [3:0] $end
$var wire 4 A" B [3:0] $end
$var wire 1 6 resta $end
$var wire 1 B" c_out $end
$var wire 4 C" S [3:0] $end
$upscope $end
$upscope $end
$scope module uc1 $end
$var wire 1 . clk $end
$var wire 3 D" q [2:0] $end
$var wire 1 : qsub1 $end
$var wire 1 2 reset $end
$var wire 1 6 Resta $end
$var wire 1 E" Reset_A $end
$var wire 1 - Fin $end
$var wire 1 ; DesplazaAQ $end
$var wire 1 < CargaQ $end
$var wire 1 = CargaM $end
$var wire 1 > CargaA $end
$var reg 3 F" estado [2:0] $end
$var reg 3 G" estado_siguiente [2:0] $end
$upscope $end
$upscope $end
$upscope $end
$enddefinitions $end
#0
$dumpvars
b1 G"
b0 F"
1E"
b0 D"
b0 C"
0B"
b0 A"
b0 @"
0?"
1>"
0="
0<"
1;"
0:"
19"
08"
07"
06"
05"
04"
03"
02"
01"
00"
0/"
0."
0-"
0,"
0+"
b0 *"
b100 )"
1("
0'"
1&"
0%"
0$"
1#"
0""
1!"
1~
0}
0|
1{
0z
0y
1x
0w
0v
0u
0t
0s
0r
0q
0p
0o
0n
0m
0l
0k
0j
b0 i
b1100 h
1g
0f
0e
0d
0c
1b
0a
0`
0_
0^
0]
1\
0[
0Z
0Y
0X
0W
0V
1U
0T
0S
0R
0Q
0P
0O
1N
0M
0L
0K
0J
b0 I
b0 H
0G
0F
b0 E
b0 D
b0 C
b0 B
1A
b100 @
b100 ?
0>
1=
1<
0;
0:
b0 9
b0 8
b0 7
06
b100 5
b100 4
b1 3
12
bx 1
b100 0
b100 /
0.
0-
b0 ,
z+
z*
z)
x(
x'
x&
x%
x$
x#
z"
z!
$end
#100
02
#500
15"
1t
0;"
17"
0#"
1}
1v
1_
1X
0>"
1<"
16"
1/"
0("
0A
0&"
1$"
0~
1|
1u
1n
0g
b1100 B
b1100 I
b1100 C"
0<
0=
0E"
13"
b100 ,
b100 9
1y
1r
b10 G"
b100 7
b100 C
b100 *"
b100 D"
1:"
1""
b1100 D
b1100 i
b1100 A"
1z
b1 F"
1.
#1000
0.
#1500
1("
1G
1A
1;
b11 G"
b10 F"
1.
#2000
0.
#2500
0("
0G
0A
0;
05"
1."
07"
10"
03"
1,"
b10 ,
b10 9
b100 G"
0:"
b10 7
b10 C
b10 *"
b10 D"
14"
b11 F"
1.
#3000
0.
#3500
1("
1G
1A
1;
b101 G"
b100 F"
1.
#4000
0.
#4500
1[
0b
1^
0\
0U
0N
0_
1>
b100 B
b100 I
b100 C"
1B"
0("
1G
0A
16
0;
0."
00"
0,"
1?"
b1 ,
b1 9
b110 G"
04"
b1 7
b1 C
b1 *"
b1 D"
1-"
b101 F"
1.
#5000
0.
#5500
1T
1V
1b
1\
1U
1N
0a
0[
1("
1A
0>
0d
0^
1;
1_
0X
b1000 B
b1000 I
b1000 C"
b111 G"
1R
b100001 ,
b100001 9
b110 F"
b100 8
b100 E
b100 H
b100 @"
1Z
1.
#6000
0.
#6500
0B"
0("
0G
0A
06
0T
1_
1X
1Q
1M
0;
b10000 1
0V
b1110 B
b1110 I
b1110 C"
1O
1-
0?"
0R
1K
b10000 ,
b10000 9
1:
b0 7
b0 C
b0 *"
b0 D"
0-"
0Z
b10 8
b10 E
b10 H
b10 @"
1S
b111 F"
1.
#7000
0.
#7500
1.
#8000
0.
#8500
1;"
1#"
1m
0t
0_
0X
0Q
0M
1>"
0<"
06"
0/"
1("
1A
1&"
0$"
1~
0|
0u
1p
0n
1g
0}
0v
b0 B
b0 I
b0 C"
0O
1<
1=
1E"
0-
0y
0r
0K
b0 ,
b0 9
b1 G"
0:
0""
b0 D
b0 i
b0 A"
0z
b0 8
b0 E
b0 H
b0 @"
0S
b0 F"
1j
1.
12
b1101 h
b101 /
b101 4
b101 ?
b10 3
#8600
02
#9000
0.
#9500
15"
1t
0;"
17"
0#"
1}
1v
0m
0>"
1<"
16"
1/"
0("
0A
0&"
1$"
0~
1|
1u
0p
1n
0g
1_
1X
1J
0<
0=
0E"
b1101 B
b1101 I
b1101 C"
b10 G"
1r
1y
13"
b100 ,
b100 9
b1 F"
1l
1z
b1101 D
b1101 i
b1101 A"
1""
b100 7
b100 C
b100 *"
b100 D"
1:"
1.
#10000
0.
#10500
1("
1G
1A
1;
b11 G"
b10 F"
1.
#11000
0.
#11500
0("
0G
0A
0;
1."
05"
10"
07"
b100 G"
1,"
03"
b10 ,
b10 9
b11 F"
14"
b10 7
b10 C
b10 *"
b10 D"
0:"
1.
#12000
0.
#12500
1("
1G
1A
1;
b101 G"
b100 F"
1.
#13000
0.
#13500
1T
1M
0b
0\
1W
0U
1P
0N
0_
0X
1Q
1>
b11 B
b11 I
b11 C"
1B"
0("
1G
0A
0;
16
0."
00"
b110 G"
1?"
0,"
b1 ,
b1 9
b101 F"
1-"
b1 7
b1 C
b1 *"
b1 D"
04"
1.
#14000
0.
#14500
0T
1O
1M
1b
1\
0W
1U
1N
0P
1("
1A
0>
1X
0J
1;"
1;
b110 B
b110 I
b110 C"
1="
1K
1'"
b11001 ,
b11001 9
b111 G"
1S
b11 8
b11 E
b11 H
b11 @"
1L
b110 F"
1.
#15000
0.
#15500
1_
0B"
0("
0G
0A
0;
b1100 1
1Q
0M
15"
06
1-
b1110 B
b1110 I
b1110 C"
0O
17"
0K
0?"
13"
b1100 ,
b1100 9
b111 F"
b1 8
b1 E
b1 H
b1 @"
0S
0-"
b100 7
b100 C
b100 *"
b100 D"
1:"
1:
1.
#16000
0.
#16500
1.
#17000
0.
#17500
1#"
1>"
0<"
06"
0/"
1("
1A
1&"
0$"
1~
0|
1w
0u
0n
1g
1;"
1t
0_
0X
0Q
1{
05"
1<
1=
1E"
0-
0="
0v
b0 B
b0 I
b0 C"
0}
07"
b1 G"
0'"
0r
0y
03"
b0 ,
b0 9
b0 F"
b0 8
b0 E
b0 H
b0 @"
0L
0l
0z
b0 D
b0 i
b0 A"
0""
b0 7
b0 C
b0 *"
b0 D"
0:"
0:
0j
1q
1.
12
b1110 h
b110 /
b110 4
b110 ?
b11 3
#17600
02
#18000
0.
#18500
15"
1m
0;"
17"
0#"
1}
1v
1o
1_
1X
1Q
0>"
1<"
16"
1/"
0("
0A
0&"
1$"
0~
1|
0w
1u
1n
0g
b1110 B
b1110 I
b1110 C"
0<
0=
0E"
13"
b100 ,
b100 9
1y
1r
1k
b10 G"
b100 7
b100 C
b100 *"
b100 D"
1:"
1""
1z
b1110 D
b1110 i
b1110 A"
1s
b1 F"
1.
#19000
0.
#19500
1("
1G
1A
1;
b11 G"
b10 F"
1.
#20000
0.
#20500
0("
0G
0A
0;
05"
1."
07"
10"
03"
1,"
b10 ,
b10 9
b100 G"
0:"
b10 7
b10 C
b10 *"
b10 D"
14"
b11 F"
1.
#21000
0.
#21500
1("
1G
1A
1;
b101 G"
b100 F"
1.
#22000
0.
#22500
1T
0b
0\
1W
0U
0N
0_
0X
1>
b10 B
b10 I
b10 C"
1B"
0("
1G
0A
16
0;
0."
00"
0,"
1?"
b1 ,
b1 9
b110 G"
04"
b1 7
b1 C
b1 *"
b1 D"
1-"
b101 F"
1.
#23000
0.
#23500
1M
1O
1b
1\
1U
1N
0[
0T
1("
1A
0>
0^
0W
1;
1X
0Q
b100 B
b100 I
b100 C"
b111 G"
1K
b10001 ,
b10001 9
b110 F"
b10 8
b10 E
b10 H
b10 @"
1S
1.
#24000
0.
#24500
1_
0B"
0("
0G
0A
06
0M
1X
1Q
1J
1;"
0;
b1000 1
0O
b1111 B
b1111 I
b1111 C"
1="
1-
0?"
0K
1'"
b1000 ,
b1000 9
1:
b0 7
b0 C
b0 *"
b0 D"
0-"
0S
b1 8
b1 E
b1 H
b1 @"
1L
b111 F"
1.
#25000
0.
#25500
1.
#26000
0.
#26500
1#"
0_
0X
0Q
0J
1>"
0<"
06"
0/"
1("
1A
1&"
0$"
1~
0|
1w
0u
1p
0n
1g
0}
0v
0o
b0 B
b0 I
b0 C"
0="
1<
1=
1E"
0-
0y
0r
0k
0'"
b0 ,
b0 9
b1 G"
0:
0""
0z
b0 D
b0 i
b0 A"
0s
b0 8
b0 E
b0 H
b0 @"
0L
b0 F"
1j
1.
12
b1111 h
b111 /
b111 4
b111 ?
b100 3
#26600
02
#27000
0.
#27500
15"
0;"
17"
0#"
1}
1v
1o
0>"
1<"
16"
1/"
0("
0A
0&"
1$"
0~
1|
0w
1u
0p
1n
0g
1_
1X
1Q
1J
0<
0=
0E"
b1111 B
b1111 I
b1111 C"
b10 G"
1k
1r
1y
13"
b100 ,
b100 9
b1 F"
1l
1s
1z
b1111 D
b1111 i
b1111 A"
1""
b100 7
b100 C
b100 *"
b100 D"
1:"
1.
#28000
0.
#28500
1("
1G
1A
1;
b11 G"
b10 F"
1.
#29000
0.
#29500
0("
0G
0A
0;
1."
05"
10"
07"
b100 G"
1,"
03"
b10 ,
b10 9
b11 F"
14"
b10 7
b10 C
b10 *"
b10 D"
0:"
1.
#30000
0.
#30500
1("
1G
1A
1;
b101 G"
b100 F"
1.
#31000
0.
#31500
1M
0b
0\
0U
1P
0N
0_
0X
0Q
1>
b1 B
b1 I
b1 C"
1B"
0("
1G
0A
0;
16
0."
00"
b110 G"
1?"
0,"
b1 ,
b1 9
b101 F"
1-"
b1 7
b1 C
b1 *"
b1 D"
04"
1.
#32000
0.
#32500
0M
1b
1\
1U
1N
0P
1("
1A
0>
1Q
0J
1;"
1;
b10 B
b10 I
b10 C"
1="
1'"
b1001 ,
b1001 9
b111 G"
b1 8
b1 E
b1 H
b1 @"
1L
b110 F"
1.
#33000
0.
#33500
1_
1X
0B"
0("
0G
0A
0;
b100 1
1Q
1J
0;"
15"
06
1-
b1111 B
b1111 I
b1111 C"
0="
17"
0'"
0?"
13"
b100 ,
b100 9
b111 F"
b0 8
b0 E
b0 H
b0 @"
0L
0-"
b100 7
b100 C
b100 *"
b100 D"
1:"
1:
1.
#34000
0.
#34500
1.
#35000
0.
#35500
1;"
1>"
0<"
06"
0/"
1("
1A
0$"
0|
0u
0n
1g
0m
0t
0_
0X
0Q
0J
0{
05"
1<
1=
1E"
0-
0o
0v
b0 B
b0 I
b0 C"
0}
07"
b1 G"
0k
0r
0y
03"
b0 ,
b0 9
b0 F"
0l
0s
0z
b0 D
b0 i
b0 A"
0""
b0 7
b0 C
b0 *"
b0 D"
0:"
0:
0!"
0j
0q
0x
1.
12
b0 h
b0 /
b0 4
b0 ?
b101 3
#35600
02
#36000
0.
#36500
15"
0;"
17"
0>"
1<"
16"
1/"
0("
0A
1$"
1|
1u
1n
0g
0<
0=
0E"
13"
b100 ,
b100 9
b10 G"
b100 7
b100 C
b100 *"
b100 D"
1:"
b1 F"
1.
#37000
0.
#37500
1("
1G
1A
1;
b11 G"
b10 F"
1.
#38000
0.
#38500
0("
0G
0A
0;
05"
1."
07"
10"
03"
1,"
b10 ,
b10 9
b100 G"
0:"
b10 7
b10 C
b10 *"
b10 D"
14"
b11 F"
1.
